{
  "la_primera": {
    "Unalm": 1,
    "Resultados": 1,
    "Casa": 2,
    "Marqués": 2,
    "Reunión": 1,
    "Decente": 1,
    "Final": 1,
    "Reforzarán": 1,
    "Lloclla": 1,
    "Debate": 1,
    "Superior": 1,
    "Distrito": 2,
    "Adultos": 1,
    "Cinco": 1,
    "Biden": 1,
    "Oficializan": 1,
    "Prensa": 1,
    "Poder": 1,
    "Ciudadana": 1,
    "Cooperación": 1,
    "Falsas": 1,
    "Víctimas": 1,
    "Elaboran": 1,
    "Abrigo": 1,
    "Horario": 1,
    "Encuestadoras": 1,
    "Elvia": 1,
    "Respuesta": 1,
    "Janeiro": 1,
    "Raymi": 1,
    "Debuta": 1,
    "Carretera": 1,
    "Continental": 1,
    "Nuevo": 2,
    "Atenciones": 1,
    "Gratuitamente": 1,
    "Papelón": 1,
    "Jangas": 1,
    "Alimento": 1,
    "Expresión": 1,
    "Jne": 2,
    "Dañan": 1,
    "Entra": 1,
    "Bomba": 1,
    "Inés": 1,
    "Reservorios": 1,
    "Empatan": 1,
    "Noticias": 1,
    "Elecciones": 2,
    "Sistema": 1,
    "Turismo": 1,
    "Presidenta": 1,
    "Violencia": 1,
    "Meses": 1,
    "Nulidad": 1,
    "Apelaciones": 1,
    "Friaje": 1,
    "Origen": 1,
    "Ventanillas": 1,
    "Realizó": 1,
    "Gestión": 1,
    "Nutricionista": 1,
    "Listo": 1,
    "Hectáreas": 1,
    "Agricultores": 1,
    "América": 2,
    "Informante": 1,
    "Selección": 2,
    "Río": 1,
    "Mal": 1,
    "Benefician": 1,
    "Distritos": 1,
    "Ampliado": 1,
    "Nube": 1,
    "Riesgo": 1,
    "Cusco": 3,
    "Ema": 1,
    "Zonas": 1,
    "Código": 1,
    "Instituto": 1,
    "Chile": 1,
    "Demora": 1,
    "Brigada": 1,
    "Covid": 1,
    "Reabren": 1,
    "Transparencia": 1,
    "Eurocopa": 1,
    "Chincha": 1,
    "Primer": 1,
    "Mina": 1,
    "Tiempo": 1,
    "Erdogan": 1,
    "Ejército": 1,
    "Pedidos": 1,
    "Rica": 1,
    "Entrenamiento": 1,
    "Pos": 1,
    "Indígenas": 1,
    "Madre": 1,
    "Fujimorista": 1,
    "Recepción": 1,
    "Dañinas": 1,
    "Bilateral": 1,
    "Cúcuta": 1,
    "Población": 1,
    "Mental": 1,
    "Millones": 2,
    "Necesario": 1,
    "Certifica": 1,
    "Plantas": 1,
    "Dentro": 1,
    "Explosión": 1,
    "Pastos": 1,
    "Barcos": 1,
    "Francia": 1,
    "Oxígeno": 1,
    "Abofeteó": 1,
    "Procesal": 1,
    "Corte": 1,
    "Renovación": 1,
    "Martín": 1,
    "Ascienden": 1,
    "Alcaldes": 1,
    "Otuzco": 1,
    "Toda": 1,
    "Electoral": 1,
    "Castillo": 3,
    "Dios": 1,
    "Essalud": 1,
    "Colombia": 2,
    "Pandemia": 1,
    "Explota": 1,
    "Entrega": 2,
    "Sahuanay": 1,
    "Confiar": 1,
    "Casos": 1,
    "Fake": 2,
    "Victoria": 1,
    "Sebastián": 1,
    "Implementará": 1,
    "Práctica": 1,
    "Vacuna": 1,
    "Argentina": 1,
    "Respaldo": 1,
    "Tunki": 1,
    "Suben": 1,
    "Mantiene": 1,
    "Barrios": 1,
    "Servicios": 1,
    "Copa": 2,
    "Pobladores": 1,
    "Playa": 1,
    "Resolver": 1,
    "Justicia": 1,
    "Warma": 1,
    "Mayores": 1,
    "Peruanos": 1,
    "Tumbes": 1,
    "Ceremonia": 1,
    "Detectar": 1,
    "Modernas": 1,
    "Iniciado": 1,
    "Judicial": 1,
    "Altamente": 1,
    "Urgente": 1,
    "Política": 1,
    "Vacunan": 1,
    "Cuatro": 1,
    "Aplicativo": 1,
    "Favor": 1,
    "Embarcó": 1,
    "Hombre": 1,
    "Messi": 1,
    "Vías": 1,
    "Contraloría": 1,
    "Mype": 1,
    "Mejorarán": 1,
    "Pánico": 1,
    "Torneo": 1,
    "Alemania": 1,
    "Prisión": 1,
    "Gaseosas": 1,
    "Advierte": 1,
    "Brindado": 1,
    "Mañana": 1,
    "Advierten": 1,
    "Loreto": 1,
    "Reapertura": 1,
    "Asesorar": 1,
    "Penal": 1,
    "News": 2,
    "Toneladas": 1,
    "Brasil": 1,
    "Oportuna": 1,
    "Naturales": 1,
    "Lima": 2,
    "Buena": 2,
    "Empleo": 1,
    "Octavio": 1,
    "Intervienen": 1,
    "Granpan": 1,
    "Muertos": 1,
    "Presentará": 1,
    "Condenan": 1,
    "Vida": 1,
    "Nueve": 1,
    "Emprendedores": 1,
    "Anuncia": 1,
    "Bocana": 1,
    "País": 1,
    "César": 1,
    "Digno": 1,
    "Heladas": 1,
    "Pública": 1,
    "Limpieza": 1,
    "Democracia": 1,
    "Santa": 1,
    "Goles": 1,
    "Quedando": 1,
    "Lanzan": 1,
    "Labores": 1,
    "Qali": 1,
    "Bicentenarias": 1,
    "Carro": 1,
    "Asegura": 1,
    "Kits": 1,
    "Choza": 1,
    "Brigadas": 1,
    "Hospitales": 1,
    "Compras": 1,
    "Proclamará": 1,
    "Explica": 1,
    "Médicas": 1,
    "Pide": 2,
    "Destinará": 1,
    "Bolívar": 1,
    "Peruana": 2,
    "China": 1,
    "Así": 1,
    "San": 2,
    "Novedades": 1,
    "Macron": 1,
    "Reúne": 1,
    "Libertad": 2,
    "Alimentos": 1,
    "Botón": 1,
    "Inti": 1,
    "Astrazeneca": 1,
    "Harakiri": 1,
    "Móviles": 1,
    "Regiones": 1,
    "Ucayali": 1,
    "Trabajo": 2,
    "Informa": 1,
    "Pedro": 2,
    "Riesgos": 1,
    "Naranja": 1,
    "Vecinales": 1,
    "Esperada": 1,
    "Pueblos": 1,
    "Nacional": 2,
    "Salud": 3,
    "Cultura": 1,
    "Sabotaje": 1,
    "Vigencia": 1,
    "Participación": 1,
    "Nutritivo": 1,
    "Falacia": 1,
    "Gris": 1
  },
  "la_republica": {
    "Sebastián": 1,
    "Netflix": 4,
    "Madueño": 2,
    "Fujimori": 1,
    "Evitar": 1,
    "Dávila": 1,
    "Landa": 1,
    "Episodio": 2,
    "Shock": 1,
    "Camaleón": 1,
    "Meses": 1,
    "Darcourt": 1,
    "López": 2,
    "Material": 1,
    "Finales": 1,
    "Aparición": 1,
    "Rápidos": 1,
    "Junio": 13,
    "Jennifer": 1,
    "Recupera": 1,
    "Cuáles": 1,
    "Miércoles": 11,
    "Quedó": 1,
    "Anahí": 1,
    "Aries": 1,
    "Gana": 1,
    "Piscis": 1,
    "Hacer": 1,
    "Hora": 3,
    "Aprovecha": 1,
    "Thriller": 1,
    "Bondad": 1,
    "Paseos": 1,
    "Cantante": 1,
    "Hart": 1,
    "Millones": 1,
    "Agradece": 1,
    "Revisa": 1,
    "Consulta": 1,
    "Cameo": 1,
    "Chile": 3,
    "Portocarrero": 1,
    "Acepte": 1,
    "Saltos": 1,
    "Trabajo": 1,
    "Dúo": 1,
    "Responde": 1,
    "Imitar": 1,
    "Serie": 1,
    "Natti": 1,
    "Suicide": 1,
    "Hoy": 12,
    "Planes": 1,
    "Despide": 2,
    "Hace": 1,
    "Lista": 1,
    "Historia": 1,
    "Quedarán": 1,
    "Emocionan": 1,
    "Resultados": 2,
    "Mediático": 1,
    "Conejo": 1,
    "Revendió": 1,
    "Flor": 1,
    "Personaje": 1,
    "Squad": 1,
    "Domínguez": 1,
    "Carrera": 1,
    "Dio": 1,
    "Derrota": 1,
    "Computadora": 1,
    "Realiza": 1,
    "Razer": 1,
    "Refugio": 1,
    "Fuerte": 1,
    "Christian": 1,
    "Canino": 1,
    "Capta": 1,
    "Mario": 1,
    "Personajes": 2,
    "Luz": 1,
    "Mendoza": 1,
    "Padecer": 1,
    "Potrillo": 1,
    "Capricornio": 1,
    "Rafael": 1,
    "Lomo": 1,
    "Culpan": 1,
    "Payne": 1,
    "Contagio": 1,
    "Favorito": 1,
    "Rivero": 1,
    "Vasco": 2,
    "James": 1,
    "Compromiso": 1,
    "Enfermedad": 1,
    "Pocos": 1,
    "Comentarios": 1,
    "Eeg": 1,
    "Daniela": 1,
    "Finalmente": 1,
    "Mejor": 1,
    "Albergue": 1,
    "Conoce": 1,
    "Merly": 1,
    "Isabelle": 1,
    "Sorpresa": 1,
    "Pequeño": 1,
    "Magaly": 1,
    "Nominados": 1,
    "Kraven": 1,
    "Capitanía": 1,
    "Gunn": 1,
    "Planta": 1,
    "Ver": 3,
    "Tauro": 1,
    "Celebra": 1,
    "Montarse": 1,
    "Inteligente": 1,
    "Reta": 1,
    "Ayuda": 1,
    "Calificación": 1,
    "Madre": 1,
    "Predicciones": 1,
    "Fuhrman": 1,
    "Jurado": 1,
    "Pidió": 1,
    "Manga": 1,
    "Mejores": 1,
    "Ponen": 1,
    "Rendí": 1,
    "Karla": 2,
    "Estreno": 5,
    "Ficción": 1,
    "Semifinal": 1,
    "Vista": 1,
    "Mamá": 1,
    "Pronuncian": 1,
    "Mira": 1,
    "Valkyrie": 1,
    "Conmueve": 1,
    "Leo": 1,
    "Store": 1,
    "Nominaciones": 1,
    "Perro": 3,
    "Voz": 5,
    "Suárez": 1,
    "Película": 2,
    "Loki": 7,
    "Vaca": 1,
    "Sagitario": 1,
    "Atlas": 1,
    "Lleva": 1,
    "Fecha": 3,
    "Teresa": 1,
    "Covid": 3,
    "Yahaira": 1,
    "Apareció": 1,
    "Juventud": 4,
    "Colombia": 1,
    "Vértiz": 1,
    "Summer": 1,
    "Enchantress": 1,
    "Rgb": 1,
    "Nuevas": 1,
    "Tarazona": 2,
    "Papá": 1,
    "Univisión": 1,
    "Saber": 1,
    "Perros": 1,
    "Dios": 1,
    "Pasó": 1,
    "Rara": 1,
    "Guty": 1,
    "Nominada": 1,
    "Sueño": 1,
    "Imitador": 1,
    "Dónde": 2,
    "Show": 1,
    "Plasencia": 1,
    "Cyberpunk": 1,
    "Retorno": 1,
    "Ciencia": 1,
    "Mea": 1,
    "Trabajadores": 1,
    "Huérfana": 1,
    "Cena": 1,
    "Villalobos": 1,
    "Increíble": 1,
    "Completo": 2,
    "Mascarilla": 1,
    "Truco": 1,
    "Cantar": 1,
    "Perú": 6,
    "Quién": 3,
    "Acompañarnos": 1,
    "Acapulco": 1,
    "Drago": 1,
    "Revela": 1,
    "Cardi": 1,
    "Protagonizará": 1,
    "Culpa": 1,
    "Retama": 1,
    "Emprendimiento": 1,
    "Junto": 1,
    "Fernández": 1,
    "Escena": 1,
    "Max": 1,
    "Titans": 1,
    "Virgo": 1,
    "Artistas": 1,
    "Esposo": 3,
    "Camine": 1,
    "Cantó": 2,
    "Sorprenden": 1,
    "Jamás": 1,
    "Perdón": 1,
    "Evento": 1,
    "Protagonista": 1,
    "Sur": 1,
    "Lanzará": 1,
    "Guillermo": 1,
    "Cristian": 1,
    "Villano": 1,
    "Ser": 1,
    "Perritos": 2,
    "Duelo": 1,
    "Record": 1,
    "Baile": 1,
    "Fallecido": 1,
    "Perrito": 1,
    "Engaño": 1,
    "Sucursal": 1,
    "Nuevo": 4,
    "Vivo": 1,
    "Noche": 2,
    "Elogia": 1,
    "Emilia": 1,
    "Korina": 1,
    "Intenta": 1,
    "Mujer": 1,
    "Huérfano": 1,
    "Feliciano": 2,
    "Logró": 2,
    "Anticipa": 1,
    "Furiosos": 1,
    "Después": 1,
    "Cáncer": 1,
    "Atención": 1,
    "Online": 1,
    "Natasha": 1,
    "Playstation": 1,
    "Premios": 4,
    "Servidores": 1,
    "Participante": 2,
    "Días": 1,
    "Carmen": 1,
    "Xbox": 2,
    "Anciano": 1,
    "Fin": 1,
    "Gatito": 1,
    "Confianza": 1,
    "Sorprende": 1,
    "Peso": 1,
    "Equivocado": 1,
    "Shuumatsu": 1,
    "Positivo": 1,
    "Cárcel": 1,
    "Parodi": 1,
    "Escorpio": 1,
    "Vota": 1,
    "Amigo": 2,
    "Reencuentran": 1,
    "Reguetón": 1,
    "Completó": 1,
    "Regresará": 1,
    "Pondré": 1,
    "Ragnarok": 1,
    "Temporada": 3,
    "Cazador": 1,
    "Jóvenes": 1,
    "Hará": 1,
    "Reina": 1,
    "Sesión": 1,
    "Black": 1,
    "Ucm": 1,
    "Advierte": 1,
    "Talento": 1,
    "Negocio": 1,
    "Visual": 1,
    "Nacer": 1,
    "Salir": 1,
    "Villana": 1,
    "Guerreros": 2,
    "Luego": 1,
    "Televisión": 1,
    "Luces": 1,
    "Uchulú": 1,
    "Adelanta": 1,
    "Nuevos": 1,
    "Onpe": 1,
    "Series": 1,
    "Karen": 1,
    "Dólares": 1,
    "Martina": 1,
    "Mtv": 1,
    "Regalarle": 1,
    "Protagonizan": 1,
    "Rating": 1,
    "Elogios": 2,
    "Bendición": 1,
    "Libra": 1,
    "Argentina": 1,
    "Retrato": 1,
    "Movimientos": 1,
    "Cárdenas": 1,
    "Cumplió": 1,
    "Recibe": 2,
    "Patricio": 1,
    "Votar": 1,
    "Cientos": 1,
    "Dentro": 1,
    "Medina": 1,
    "Flores": 1,
    "Artista": 2,
    "Gta": 1,
    "Vacunación": 1,
    "Bajo": 1,
    "Entrenadores": 1,
    "Adopción": 1,
    "Gracias": 1,
    "Pedro": 1,
    "Adoptados": 1,
    "Discapacidad": 1,
    "Noire": 1,
    "Completa": 1,
    "Adopta": 1,
    "Cerrarán": 1,
    "Tierna": 1,
    "John": 1,
    "Excelente": 1,
    "Coche": 1,
    "Demasiado": 1,
    "Pasos": 1,
    "Shore": 1,
    "Martes": 1,
    "Schwarz": 1,
    "Respete": 1,
    "Intención": 1,
    "Incentivar": 1,
    "Capítulo": 6,
    "Hombre": 1,
    "Termina": 1,
    "Orgullosos": 1,
    "Recaudar": 1,
    "Aquí": 1,
    "Inesperada": 1,
    "Horóscopo": 12,
    "Joven": 1,
    "Episodios": 1,
    "Reality": 1,
    "Pronósticos": 1,
    "José": 2,
    "Hilarante": 1,
    "Nueva": 2,
    "Programa": 1,
    "Lady": 2,
    "Keiko": 1,
    "Obsequian": 1,
    "Infidelidad": 2,
    "Rivadeneira": 1,
    "Filtrado": 1,
    "Democracia": 1
  },
  "exitosa": {
    "Metropolitana": 1,
    "Positivos": 1,
    "Kevin": 1,
    "Serie": 1,
    "Quieren": 1,
    "Cifra": 2,
    "Próximos": 1,
    "Suponga": 1,
    "Salvan": 1,
    "Tok": 1,
    "Ricardo": 1,
    "Ballena": 1,
    "Asistirán": 1,
    "Vamos": 1,
    "García": 1,
    "Modernizará": 1,
    "Apoyo": 1,
    "Entregar": 1,
    "Golpe": 1,
    "Mejores": 1,
    "Hoc": 1,
    "Realizará": 1,
    "Tercera": 1,
    "Tacna": 1,
    "Guillermo": 2,
    "Observará": 1,
    "Bajan": 1,
    "Línea": 2,
    "Gordo": 1,
    "Covid": 15,
    "Opositor": 1,
    "Putin": 1,
    "Supersónicos": 1,
    "Hernando": 1,
    "Redes": 2,
    "Repercusión": 1,
    "Hijo": 1,
    "Defensa": 1,
    "Incorporación": 1,
    "Medidas": 1,
    "Minsa": 3,
    "Mil": 5,
    "Urna": 1,
    "Uci": 1,
    "Desarrollan": 1,
    "Huilca": 1,
    "Salas": 1,
    "Conteo": 1,
    "Acabará": 1,
    "Podrían": 1,
    "Encuentra": 1,
    "Campaña": 1,
    "Edwar": 1,
    "Designa": 1,
    "Nulidad": 3,
    "Dice": 3,
    "Opecu": 1,
    "Reduce": 1,
    "Independientes": 1,
    "Advierte": 1,
    "Procesos": 1,
    "Ocaña": 1,
    "Misa": 1,
    "Cronograma": 1,
    "Onpe": 3,
    "Invoquen": 1,
    "Semipresenciales": 1,
    "Sujeto": 1,
    "Kong": 1,
    "José": 3,
    "Carlos": 2,
    "Denuncias": 3,
    "Contabilizadas": 1,
    "Causa": 1,
    "India": 2,
    "Junio": 3,
    "Debate": 1,
    "Fría": 1,
    "Fuerza": 6,
    "Detectada": 1,
    "Indira": 1,
    "Evo": 1,
    "Vuelta": 5,
    "Presidente": 7,
    "Fraude": 4,
    "Políticos": 1,
    "Falsas": 1,
    "Uso": 2,
    "Jueves": 1,
    "Sacerdote": 1,
    "Parte": 2,
    "Reunión": 1,
    "Rápido": 1,
    "Israel": 1,
    "Chicos": 1,
    "Lgbtiq": 1,
    "Mototaxistas": 1,
    "Virtual": 1,
    "Verdadero": 2,
    "Anuncian": 1,
    "Víctima": 2,
    "Alcanza": 1,
    "Respetar": 2,
    "Luego": 1,
    "Producción": 1,
    "Sino": 1,
    "Democrático": 1,
    "Nivel": 1,
    "Calles": 1,
    "Fraudulento": 1,
    "Defensoría": 1,
    "Símbolo": 1,
    "Solo": 3,
    "República": 1,
    "Parlamento": 1,
    "Calificó": 1,
    "Pusieron": 1,
    "Título": 1,
    "Marxismo": 1,
    "Universitario": 1,
    "Pueblo": 2,
    "Oms": 2,
    "Vladimir": 4,
    "Pasa": 1,
    "Cúcuta": 1,
    "Atropelló": 1,
    "Interés": 1,
    "Segundo": 1,
    "Actas": 4,
    "Obra": 1,
    "Controlada": 1,
    "Recorrer": 1,
    "Hoy": 3,
    "Acelerarse": 1,
    "Traga": 1,
    "Maquille": 1,
    "Cuota": 1,
    "Donar": 1,
    "Cusco": 1,
    "Continental": 1,
    "Transparencia": 1,
    "Alcalde": 1,
    "Vacunación": 5,
    "Excesivas": 1,
    "Representantes": 1,
    "Mesías": 2,
    "Cientos": 1,
    "Pedido": 1,
    "Obstaculizado": 1,
    "Impedimento": 1,
    "Voten": 1,
    "Protestan": 1,
    "Belaundista": 1,
    "Aníbal": 3,
    "Tripulada": 1,
    "Médico": 1,
    "Varón": 1,
    "Cuáles": 1,
    "Contener": 2,
    "Construir": 1,
    "Mesa": 1,
    "Sagasti": 2,
    "Variante": 4,
    "Acción": 1,
    "Humanos": 1,
    "Millones": 2,
    "Paciencia": 1,
    "Comprueba": 1,
    "Audiencia": 1,
    "Aclaran": 1,
    "Robar": 1,
    "Afirma": 1,
    "Iniciado": 1,
    "Cueva": 1,
    "Diresa": 1,
    "Santos": 2,
    "Tumbarse": 1,
    "Biden": 1,
    "Brasil": 3,
    "Iquitos": 1,
    "Familia": 4,
    "Presenta": 1,
    "Boca": 1,
    "Billetes": 1,
    "Debe": 3,
    "Gianluca": 1,
    "Barbarán": 1,
    "Julio": 4,
    "Alerta": 2,
    "Cerrados": 1,
    "Mueren": 1,
    "Incinerar": 1,
    "Nacionales": 1,
    "Llica": 1,
    "Denunciar": 1,
    "Casos": 1,
    "Piurano": 1,
    "Inmunizada": 1,
    "Incitando": 1,
    "Agua": 1,
    "Sigue": 2,
    "Recibió": 1,
    "Salvar": 1,
    "Marchas": 2,
    "Reserva": 1,
    "Subastan": 1,
    "Implementará": 1,
    "Acoso": 1,
    "Leguleyadas": 1,
    "Michelle": 2,
    "Poder": 1,
    "Dos": 3,
    "Soifer": 2,
    "Fumigando": 1,
    "Nasca": 1,
    "Tomar": 1,
    "Rostro": 1,
    "Mencionen": 1,
    "Debemos": 1,
    "Leninismo": 1,
    "Marcharán": 1,
    "Vidas": 1,
    "Kenji": 1,
    "Francisco": 1,
    "Lima": 4,
    "Quiroga": 1,
    "Prisión": 1,
    "Revelan": 1,
    "Darcourt": 1,
    "Caiga": 1,
    "Cerrón": 5,
    "Soberanía": 1,
    "Combustibles": 1,
    "Votantes": 1,
    "Deberá": 2,
    "Vivo": 2,
    "Probarlo": 1,
    "Ugarte": 1,
    "Cargo": 1,
    "Desconocer": 1,
    "Convertido": 1,
    "Bomba": 1,
    "Proclamación": 2,
    "Ciudadanía": 1,
    "Periodista": 1,
    "Reja": 1,
    "Minerales": 1,
    "Profesionales": 1,
    "Casas": 1,
    "Exorcizar": 1,
    "Chachapoyas": 1,
    "Martín": 1,
    "Opinión": 3,
    "Profesor": 1,
    "Brigada": 1,
    "Manejo": 1,
    "Imparcialidad": 1,
    "Rechazó": 1,
    "Considerado": 1,
    "Comunismo": 2,
    "Elimina": 2,
    "Salud": 1,
    "Mensaje": 1,
    "Muertos": 1,
    "Reveló": 1,
    "Escenarios": 1,
    "Justicia": 1,
    "Día": 1,
    "Aire": 1,
    "Mientras": 1,
    "Intentó": 1,
    "Pide": 4,
    "Periodismo": 1,
    "Hacer": 1,
    "Dennis": 1,
    "Potenciar": 1,
    "Evitar": 1,
    "Devolución": 1,
    "Oficiales": 2,
    "Daniela": 1,
    "Permitirá": 2,
    "Ebrio": 1,
    "Camino": 1,
    "Ley": 1,
    "Pronto": 1,
    "Gana": 1,
    "Mostró": 1,
    "Caso": 2,
    "Obtiene": 1,
    "Exteriores": 1,
    "Abogado": 1,
    "Aludido": 1,
    "Llevado": 1,
    "Palacio": 1,
    "Keiko": 9,
    "Crecimiento": 1,
    "Petroleras": 1,
    "Bermejo": 2,
    "Márquez": 1,
    "Prudente": 1,
    "Fujimorismo": 1,
    "Quiera": 1,
    "Vacunó": 1,
    "Electo": 2,
    "Democracia": 1,
    "Rafael": 2,
    "Sociales": 2,
    "Cielos": 1,
    "Enrique": 1,
    "Montoya": 3,
    "Ofrecen": 1,
    "Aclarar": 1,
    "Vestida": 1,
    "Nombre": 1,
    "Rospigliosi": 1,
    "Mató": 1,
    "Exportaciones": 1,
    "Gobierno": 6,
    "Tirar": 1,
    "Incentivar": 1,
    "Sacrificio": 1,
    "Electoral": 7,
    "Conocer": 1,
    "Madre": 2,
    "Solar": 1,
    "Registró": 1,
    "Sine": 1,
    "Golpistas": 1,
    "Joe": 1,
    "Jugar": 1,
    "Comunista": 1,
    "Capturan": 1,
    "Pedro": 9,
    "Buscando": 1,
    "Vida": 2,
    "Dañado": 1,
    "Apelaciones": 2,
    "Morales": 1,
    "Resultados": 9,
    "Fujimori": 8,
    "Listos": 1,
    "Paz": 1,
    "Nuevas": 2,
    "Detectó": 1,
    "Piden": 1,
    "Comunicar": 1,
    "Lanzará": 1,
    "Indicó": 1,
    "Casi": 1,
    "Público": 1,
    "Recuperarse": 1,
    "Fallecido": 1,
    "Autoridades": 1,
    "Publicidad": 1,
    "Argentina": 1,
    "Patria": 1,
    "Violencia": 1,
    "Enluta": 1,
    "Pandemia": 3,
    "Horas": 1,
    "Independencia": 2,
    "Veterano": 1,
    "Guerra": 2,
    "Fonavistas": 1,
    "Pareja": 1,
    "Vacunados": 1,
    "Protegida": 1,
    "Callao": 2,
    "Requerimiento": 1,
    "Miraflores": 1,
    "Silla": 1,
    "Financiamiento": 1,
    "Bolivia": 1,
    "Pfizer": 1,
    "Circulación": 1,
    "Inicio": 1,
    "Jugaría": 1,
    "Popular": 8,
    "Hurtan": 1,
    "Crecieron": 1,
    "Expareja": 1,
    "News": 1,
    "Entrenamiento": 1,
    "Reapareció": 1,
    "Científico": 1,
    "Demócratas": 1,
    "Dilatar": 2,
    "Laynes": 2,
    "Vendían": 1,
    "Llamando": 1,
    "Blooper": 1,
    "Votar": 1,
    "Revela": 1,
    "Emprendimiento": 1,
    "Ceremonia": 1,
    "Creó": 1,
    "Arequipa": 10,
    "China": 1,
    "Acciones": 2,
    "Ronderos": 1,
    "Deslegitimado": 1,
    "Visita": 1,
    "Aplicaciones": 1,
    "Negocio": 1,
    "Comete": 1,
    "Exige": 1,
    "Chiflados": 1,
    "Die": 1,
    "Toque": 1,
    "Frida": 2,
    "Vacunas": 2,
    "Denuncia": 2,
    "Ganado": 1,
    "Periodo": 1,
    "Tragedia": 1,
    "Dinámicos": 1,
    "Socialismo": 1,
    "Pokémon": 1,
    "Industrial": 1,
    "Abogados": 1,
    "Mandó": 1,
    "Mendoza": 1,
    "Moe": 1,
    "Diferencia": 1,
    "Nuevo": 1,
    "Sabemos": 1,
    "Poner": 1,
    "Libro": 1,
    "Públicos": 1,
    "Dina": 1,
    "Arenas": 1,
    "Bastante": 1,
    "Detectar": 1,
    "Dinamarca": 1,
    "Explotó": 1,
    "Muerte": 1,
    "Plena": 1,
    "Personas": 3,
    "Huyen": 1,
    "Afirmó": 1,
    "Cuatro": 1,
    "Legal": 2,
    "Internacionales": 1,
    "Abuso": 1,
    "Critica": 1,
    "Van": 1,
    "Todavía": 1,
    "Sofía": 2,
    "Laboral": 1,
    "Tres": 2,
    "Melody": 1,
    "Descartó": 2,
    "Boluarte": 1,
    "Inicia": 1,
    "Gareca": 1,
    "Bazán": 2,
    "Sexual": 1,
    "Vuelven": 1,
    "Shakespeare": 1,
    "Formal": 1,
    "Pronombres": 1,
    "Piura": 1,
    "Mar": 1,
    "Luna": 1,
    "Multa": 1,
    "Delta": 2,
    "Den": 1,
    "Aún": 1,
    "España": 1,
    "Barnechea": 1,
    "Humano": 1,
    "Observadas": 2,
    "Probable": 1,
    "Padre": 1,
    "Policías": 1,
    "Aviones": 1,
    "Tik": 1,
    "Congreso": 2,
    "Alto": 2,
    "Lograr": 1,
    "Respetará": 1,
    "Hija": 1,
    "Viajaba": 1,
    "Christian": 3,
    "Acudió": 1,
    "Concierto": 1,
    "Dicen": 1,
    "Poquito": 1,
    "Caer": 1,
    "Asegura": 5,
    "Usar": 1,
    "Ruedas": 1,
    "Base": 1,
    "Lado": 1,
    "Autoridad": 1,
    "Castillo": 12,
    "Perfil": 1,
    "Dramaturgo": 1,
    "Aplican": 1,
    "Trujillo": 2,
    "Eliminar": 1,
    "Domicilio": 1,
    "Cardíacos": 1,
    "Dorsal": 1,
    "Luis": 2,
    "Comisión": 2,
    "Lambda": 1,
    "Combina": 1,
    "Pareció": 1,
    "Artista": 1,
    "Toda": 1,
    "Diversas": 1,
    "Cerveza": 1,
    "Asociados": 1,
    "Rennán": 1,
    "Rechazamos": 1,
    "Ecuador": 1,
    "Virtualmente": 1,
    "Torres": 4,
    "Falvy": 1,
    "Alza": 1,
    "Importancia": 1,
    "Avance": 1,
    "Organizar": 1,
    "Cobre": 1,
    "Mypes": 1,
    "Aprista": 1,
    "Ratifica": 1,
    "Minutos": 1,
    "Todas": 1,
    "Espinoza": 1,
    "Advierten": 1,
    "Disputar": 1,
    "Estima": 1,
    "Población": 1,
    "Claves": 1,
    "Allá": 1,
    "Droga": 1,
    "Andino": 1,
    "Nacional": 1,
    "Esposos": 1,
    "Matrimonio": 1,
    "Destacó": 1,
    "Norma": 1,
    "Sistema": 1,
    "Irregularidades": 2,
    "Hallan": 1,
    "Queda": 1,
    "Podemos": 2,
    "Fernando": 1,
    "Revise": 1,
    "Física": 1,
    "Vizcarra": 1,
    "Igualitario": 1,
    "Salvador": 1,
    "Cuándo": 1,
    "Reportó": 1,
    "Dólares": 1,
    "Problema": 1,
    "Viaja": 2,
    "Carro": 1,
    "Sujetos": 1,
    "Elice": 1,
    "Estudia": 1,
    "Lescano": 1,
    "Adelantó": 1,
    "Urviola": 1,
    "Guevara": 3,
    "Ninguna": 1,
    "Pacíficas": 1,
    "Atenta": 1,
    "Pez": 1,
    "Suba": 1,
    "Jorge": 2,
    "Discurso": 1,
    "Cerrar": 1,
    "Pedir": 3,
    "Debían": 1,
    "Reality": 1,
    "Reconocer": 1,
    "Villasana": 1,
    "Ambición": 1,
    "Borde": 1,
    "Libertad": 2,
    "Mundial": 1,
    "Selección": 5,
    "Elección": 3,
    "Capítulos": 1,
    "Instancia": 1,
    "Rechazo": 1,
    "Hong": 1,
    "Arranca": 1,
    "Nulidades": 1,
    "Trabajar": 1,
    "Tomando": 1,
    "Explosión": 2,
    "Blow": 1,
    "Acepta": 1,
    "Ejército": 1,
    "Asesinadas": 1,
    "Mujer": 1,
    "Acto": 1,
    "Anular": 1,
    "Observadores": 1,
    "Boda": 1,
    "Lugares": 1,
    "Mujeres": 3,
    "Emprender": 1,
    "Mayores": 1,
    "Histórica": 1,
    "Cinco": 2,
    "Asesinatos": 1,
    "Normalizar": 1,
    "Amenazan": 1,
    "Desconocimiento": 1,
    "Perú": 10,
    "Euros": 2,
    "Instagram": 1,
    "Desmonte": 1,
    "Navalni": 1,
    "Congresistas": 1,
    "Número": 1,
    "Basura": 2,
    "Formas": 1,
    "Invitar": 1,
    "Spelucin": 1,
    "Protestas": 1,
    "Protestar": 1,
    "Suma": 1,
    "Proceso": 6,
    "Cercado": 1,
    "William": 1,
    "Quiere": 1,
    "Función": 1,
    "Recuperadas": 1,
    "Cementerio": 1,
    "Unidos": 2,
    "Empezará": 1,
    "Utilizará": 1,
    "Recibir": 1,
    "Razón": 1,
    "Tiempos": 1,
    "Elecciones": 6,
    "Sanitarias": 1,
    "Lapadula": 2,
    "Llamados": 1,
    "Misión": 1,
    "Sector": 1,
    "Casa": 1,
    "Dentro": 1,
    "Copa": 3,
    "Bruce": 2,
    "Concentradores": 1,
    "Protegerse": 1,
    "Resolver": 2,
    "Raymi": 1,
    "Bosque": 1,
    "Cueto": 1,
    "América": 3,
    "Peruana": 3,
    "Informales": 1,
    "Retorno": 1,
    "Fake": 1,
    "Centros": 1,
    "Inclusión": 1,
    "Ponerse": 1,
    "Spelucín": 1,
    "Reconocimiento": 1,
    "Flujo": 1,
    "Bullying": 1,
    "Valer": 1,
    "Sinaloa": 1,
    "Sunat": 1,
    "Morada": 1,
    "Sigrid": 2,
    "Nueva": 1,
    "Magistrado": 1,
    "Enfrenta": 1,
    "Electorales": 3,
    "Segunda": 6,
    "Española": 1,
    "Irrumpieron": 1,
    "Eriksen": 2,
    "Parejas": 1,
    "Tecnológico": 2,
    "Pacientes": 1,
    "Tragamonedas": 1,
    "Partido": 1,
    "Indisciplina": 1,
    "Libre": 5,
    "Oculares": 1,
    "Mascarilla": 3,
    "Yonhy": 1,
    "Ser": 3,
    "Chan": 2,
    "Ormeño": 1,
    "Cursos": 1,
    "Carta": 1,
    "Amedrentar": 1,
    "Puedes": 1,
    "Quedarte": 1,
    "Extraña": 1,
    "Voces": 1,
    "Deficiente": 1,
    "Multas": 2,
    "Dejará": 1,
    "México": 1,
    "Bajando": 1,
    "Sangre": 1,
    "Donante": 1,
    "País": 3,
    "Varios": 1,
    "Importa": 1,
    "Acusaciones": 1,
    "Ningún": 1,
    "Pescador": 1,
    "Debido": 1,
    "Clases": 1,
    "Inti": 1,
    "Citas": 1,
    "Proclamará": 1,
    "Pony": 1,
    "Economía": 1,
    "Hablado": 1,
    "Sufragar": 1,
    "Oposición": 1,
    "Jne": 13,
    "Acá": 1,
    "Tampoco": 1,
    "Cevallos": 1,
    "Problemas": 1,
    "Precio": 1,
    "Cometió": 1,
    "Salida": 1,
    "Devora": 1,
    "Bancada": 2,
    "Hará": 1,
    "Podría": 1,
    "Francia": 3,
    "Niños": 1,
    "Congresista": 2,
    "Haciendo": 1,
    "Acusar": 1,
    "Transporte": 1,
    "Mata": 1,
    "Humedales": 1,
    "Esperará": 1,
    "Pretendían": 1,
    "Voluntad": 1,
    "Oxígeno": 2,
    "Primera": 2,
    "Espacial": 1,
    "Escuche": 1,
    "Obligatorio": 1,
    "Regiones": 1,
    "Error": 1,
    "Fallecidos": 2,
    "Pesca": 1,
    "Saber": 1,
    "Eventual": 1,
    "Movimientos": 1,
    "Semana": 1,
    "Autoriza": 1,
    "Muerto": 1,
    "Permanece": 1,
    "César": 1,
    "Afirmar": 1,
    "Usuarios": 1,
    "Alfredo": 1,
    "Camas": 1,
    "Abril": 1,
    "Solís": 1,
    "Favorecer": 1,
    "Valdés": 1,
    "Centro": 1,
    "Virgen": 1,
    "Padrón": 1,
    "Jauría": 1,
    "Ministro": 1,
    "Disculparse": 1,
    "Falsos": 1,
    "Abuelo": 1,
    "Guzmán": 3,
    "Loreto": 1,
    "Anunció": 1,
    "Declarar": 1,
    "Sistemático": 1,
    "Aprobó": 1,
    "Tiempo": 2,
    "Colapso": 1,
    "Ola": 1,
    "Colocar": 1,
    "Toneladas": 2,
    "Vacuna": 2,
    "Participe": 1,
    "Huamanga": 1,
    "Colombia": 1,
    "Lamenta": 1,
    "Superficial": 1,
    "Vez": 1,
    "Unido": 1,
    "Miguel": 1,
    "Amerita": 1,
    "Google": 1,
    "Rusia": 2,
    "Naupari": 1,
    "Pagar": 1,
    "Química": 1,
    "Escupe": 1
  },
  "ojo": {
    "Apareció": 1,
    "Avanzado": 1,
    "Fujimori": 2,
    "Debería": 2,
    "Lengua": 1,
    "Toque": 1,
    "Recomienda": 1,
    "Cerrón": 1,
    "Guerrero": 1,
    "Callao": 1,
    "Argentino": 1,
    "Nueva": 1,
    "Cumpleaños": 1,
    "Licencia": 1,
    "Beto": 1,
    "Abre": 1,
    "Ojo": 1,
    "Lucha": 1,
    "Bebés": 1,
    "Datos": 1,
    "Socialismo": 1,
    "Asisten": 1,
    "Hijo": 1,
    "Paolo": 1,
    "Profesor": 1,
    "Huele": 1,
    "Mujer": 1,
    "Postizos": 1,
    "Engreírlos": 1,
    "Verdadero": 1,
    "Pueden": 1,
    "Farfán": 1,
    "Jennifer": 1,
    "Foto": 1,
    "Bicolor": 1,
    "Trabajo": 1,
    "Jefferson": 1,
    "Segunda": 4,
    "Libre": 2,
    "Nulidad": 1,
    "Agua": 1,
    "Twitter": 1,
    "Casi": 1,
    "Bermejo": 1,
    "Perrito": 1,
    "Llegar": 1,
    "Affleck": 1,
    "Encajar": 1,
    "Fútbol": 1,
    "Cuáles": 1,
    "Anuncia": 1,
    "Divorcio": 1,
    "Injusto": 1,
    "Solicitar": 2,
    "Primera": 1,
    "Capta": 2,
    "Extranjera": 1,
    "Duelo": 1,
    "Hermanos": 1,
    "Piero": 1,
    "Horario": 1,
    "Faltar": 1,
    "Flor": 1,
    "Quieres": 1,
    "Gestantes": 1,
    "Nuevos": 1,
    "Vela": 1,
    "Auto": 1,
    "Puedo": 1,
    "Susto": 1,
    "Nacimiento": 1,
    "Perú": 4,
    "Lucir": 1,
    "Siguen": 1,
    "Nominadas": 1,
    "Cifra": 1,
    "Piercing": 1,
    "Corte": 1,
    "Embarazo": 1,
    "Susy": 1,
    "Peruanos": 1,
    "Categoría": 1,
    "Pasar": 1,
    "Historia": 1,
    "Aquí": 2,
    "Peruano": 1,
    "Misma": 1,
    "Medina": 1,
    "Pensiones": 1,
    "Debut": 1,
    "Nuevo": 1,
    "Calle": 1,
    "Destaca": 1,
    "Virtual": 1,
    "Abundante": 1,
    "Elecciones": 3,
    "Horas": 1,
    "India": 1,
    "Darcourt": 1,
    "Vigencia": 1,
    "Pass": 1,
    "Sentir": 1,
    "Quién": 1,
    "Testigo": 1,
    "Incapaz": 1,
    "Puede": 2,
    "Simpatizantes": 1,
    "Patricio": 2,
    "Gareca": 1,
    "Así": 1,
    "Tik": 1,
    "Guty": 1,
    "Rechazó": 1,
    "Queda": 1,
    "Hizo": 1,
    "América": 5,
    "Hace": 1,
    "Subsidio": 1,
    "Actas": 1,
    "Recibido": 1,
    "Morir": 1,
    "Iniciaría": 1,
    "Anticuerpos": 1,
    "Erick": 1,
    "Cateriano": 1,
    "Falta": 1,
    "Exteriores": 1,
    "Gobierno": 2,
    "Conozca": 1,
    "Tener": 1,
    "Muestra": 1,
    "Material": 1,
    "Actualizar": 1,
    "López": 1,
    "Presidente": 1,
    "Hechas": 1,
    "Juventud": 1,
    "Apoyo": 1,
    "Tips": 1,
    "Gigante": 1,
    "Sumatra": 1,
    "Aleja": 1,
    "Yahaira": 1,
    "Vacuna": 1,
    "Pandemia": 3,
    "Boda": 1,
    "Llevado": 1,
    "Maquillaje": 2,
    "Link": 1,
    "Caer": 1,
    "Jugadores": 1,
    "Coronavirus": 1,
    "Miércoles": 1,
    "Quiénes": 1,
    "Cobrar": 1,
    "Pasó": 1,
    "Recibe": 1,
    "Pleno": 1,
    "Presentadas": 1,
    "Juntos": 1,
    "Cristiano": 1,
    "Retiro": 2,
    "Kyara": 1,
    "Melena": 1,
    "Gracias": 1,
    "Votos": 1,
    "Pedro": 6,
    "Vladimir": 1,
    "Domingo": 1,
    "Comunismo": 1,
    "Dos": 1,
    "Segundos": 1,
    "Confirmado": 1,
    "Soles": 1,
    "Barcelona": 1,
    "Famosos": 1,
    "Imparcial": 1,
    "Tarot": 1,
    "Ronaldo": 1,
    "Hospital": 1,
    "Continúan": 1,
    "Pasa": 1,
    "Ivana": 1,
    "Mil": 1,
    "Incómodo": 2,
    "Yturbe": 1,
    "Alentador": 1,
    "Junto": 1,
    "Apelaciones": 1,
    "Copa": 4,
    "Removerle": 1,
    "Mensaje": 1,
    "Millones": 1,
    "Eleva": 1,
    "Socavón": 1,
    "Requieren": 1,
    "Tarjeta": 1,
    "Vizcarra": 1,
    "Piscina": 1,
    "Bono": 1,
    "Multitudes": 1,
    "Egoísmo": 1,
    "Keiko": 2,
    "Comparar": 1,
    "Suceso": 1,
    "Incompletos": 1,
    "Ben": 1,
    "Vuelta": 4,
    "Tok": 1,
    "Electrónico": 1,
    "Peor": 1,
    "Silva": 1,
    "Gian": 1,
    "Mal": 1,
    "Vacunas": 1,
    "Saber": 1,
    "Coca": 1,
    "Universitarios": 1,
    "Hacerlo": 1,
    "Ormeño": 1,
    "Premios": 1,
    "Diez": 1,
    "Errores": 1,
    "Junio": 1,
    "Castillo": 4,
    "Supera": 1,
    "Tite": 1,
    "Cola": 1,
    "Presidenciales": 1,
    "Momento": 3,
    "Paranormal": 1,
    "Toda": 1,
    "Europeos": 1,
    "Chapatucaviar": 1,
    "Desaparece": 1,
    "Minsa": 2,
    "Villanella": 1,
    "Padre": 2,
    "Mira": 1,
    "Comportamiento": 1,
    "Martín": 1,
    "Titán": 1,
    "Carne": 1,
    "Leninismo": 1,
    "Díaz": 2,
    "Ser": 3,
    "Transmite": 1,
    "Plasencia": 1,
    "Onpe": 2,
    "Triunfo": 1,
    "Todavía": 1,
    "Vacunan": 1,
    "Hombre": 1,
    "Magaly": 1,
    "Crearon": 1,
    "Banco": 1,
    "Hora": 1,
    "Atrajo": 1,
    "Transforma": 1,
    "Guillermo": 1,
    "Proyecto": 1,
    "Usar": 1,
    "Extremo": 1,
    "Cuesta": 1,
    "Adultos": 1,
    "Desgarradora": 1,
    "Joven": 1,
    "Pueblo": 2,
    "Tres": 1,
    "Cabello": 2,
    "Lapadula": 2,
    "Nadie": 1,
    "Miedo": 1,
    "Impresionó": 1,
    "Vestuario": 1,
    "Proclame": 1,
    "Decesos": 1,
    "Amatista": 1,
    "Osores": 1,
    "Especial": 1,
    "Conoce": 1,
    "Preferencial": 1,
    "Contabilizadas": 1,
    "Sabes": 1,
    "Asqueroso": 1,
    "Niños": 1,
    "Christian": 2,
    "Maradona": 1,
    "Contagios": 1,
    "Eurocopa": 1,
    "Deben": 1,
    "Inmunizados": 1,
    "Soñado": 1,
    "Gratis": 1,
    "Cerebro": 1,
    "Moda": 1,
    "Tipo": 1,
    "Messi": 2,
    "Provincias": 1,
    "Sospechas": 1,
    "Vida": 1,
    "Futbolistas": 1,
    "Culpa": 1,
    "Brasil": 2,
    "Botellas": 1,
    "Prefiere": 1,
    "Gianluca": 2,
    "Fondos": 1,
    "Principal": 1,
    "Recréalo": 1,
    "Hijas": 1,
    "Riesgos": 1,
    "Covid": 7,
    "Francke": 1,
    "Partida": 1,
    "Color": 1,
    "Estrena": 1,
    "Netflix": 1,
    "Jne": 4,
    "Cuenta": 1,
    "Horrible": 1,
    "Parodi": 1,
    "Eriksen": 1,
    "Canjear": 1,
    "Grupo": 1,
    "Chama": 1,
    "Encuentran": 1,
    "Apoya": 1,
    "Fácil": 1,
    "Afp": 2,
    "Enano": 1,
    "Pedir": 1,
    "Parte": 1,
    "Ganador": 1,
    "Varsovia": 1,
    "Homenaje": 1,
    "Después": 1,
    "Dientes": 1,
    "Realidad": 1,
    "Vez": 1,
    "Michelle": 1,
    "Días": 1,
    "Festeja": 1,
    "Soifer": 1,
    "Blusas": 1,
    "Transmiten": 1,
    "Reporta": 1,
    "Casar": 1,
    "Esposas": 1,
    "Desprecia": 1,
    "Saludo": 1,
    "Aguantan": 1,
    "Horóscopo": 1,
    "Carrera": 1,
    "Tierna": 1,
    "Hoy": 1,
    "Quiebra": 1,
    "Clóset": 1,
    "Asegura": 1,
    "Kaori": 1,
    "Documento": 1,
    "Curich": 1,
    "Foquita": 1,
    "Julio": 1,
    "Carta": 1,
    "Camiseta": 1,
    "Explica": 1,
    "Reniec": 1,
    "Pelusa": 1,
    "Tendencias": 1,
    "Recordar": 1,
    "Crítico": 1,
    "Sufrió": 1,
    "Psicológico": 1,
    "Lima": 2,
    "Loustau": 1,
    "Beber": 1,
    "Apagó": 1,
    "Pinta": 1,
    "Agresiones": 1,
    "Bien": 1,
    "Virus": 1,
    "Importantes": 1,
    "Aceptación": 1,
    "Conducir": 1,
    "Sheylón": 1,
    "Daniela": 1,
    "Casa": 1,
    "Cuestionada": 1,
    "Podrida": 1,
    "Lleva": 1,
    "Graduación": 1,
    "Fuerza": 1,
    "Día": 1,
    "Vacunación": 1,
    "Peinar": 1,
    "Cueva": 1,
    "Cuándo": 1,
    "Tarazona": 1,
    "Previa": 1,
    "Torneo": 1,
    "Metropolitano": 1,
    "Volverá": 1,
    "Hacer": 1,
    "Karla": 1,
    "Riesgo": 1
  },
  "trome": {
    "Lloró": 1,
    "Partido": 2,
    "Marcelo": 1,
    "Anota": 1,
    "Ancashino": 1,
    "Sorprenderlo": 1,
    "Copa": 4,
    "Prohibido": 1,
    "Natalie": 1,
    "Yturbe": 1,
    "Taladro": 1,
    "Hoy": 3,
    "Cueva": 8,
    "Miguel": 2,
    "Posible": 1,
    "Suspensión": 1,
    "Adolescente": 1,
    "Trome": 1,
    "Briyit": 1,
    "Empatía": 1,
    "Diario": 1,
    "Junio": 2,
    "Dos": 1,
    "Ivana": 1,
    "Recuperarse": 1,
    "Termina": 1,
    "Puede": 3,
    "Karen": 1,
    "Mil": 2,
    "Protagonizan": 1,
    "Horóscopo": 1,
    "Maltrato": 1,
    "Personaje": 1,
    "Advertencia": 1,
    "Aniversario": 1,
    "Pausini": 1,
    "Rica": 1,
    "Fechas": 1,
    "Vértiz": 1,
    "Garner": 1,
    "Vida": 1,
    "Habla": 2,
    "Karla": 1,
    "Pobreza": 1,
    "Puedo": 1,
    "Transmitirán": 1,
    "Liberan": 1,
    "Participación": 1,
    "Show": 1,
    "Descartó": 1,
    "Hijos": 1,
    "Hombres": 1,
    "Manco": 1,
    "Ternura": 1,
    "Chocolate": 1,
    "Cuenta": 1,
    "Vieth": 1,
    "Feos": 1,
    "Destruye": 1,
    "Afp": 4,
    "Muestra": 1,
    "Zapatillas": 1,
    "Pacheco": 1,
    "Llaja": 1,
    "Especial": 1,
    "Imitadora": 1,
    "Biden": 1,
    "Guía": 1,
    "Debut": 1,
    "Darse": 1,
    "Tarazona": 1,
    "Cuáles": 1,
    "Detenidos": 1,
    "Neuromarketing": 1,
    "Acusó": 1,
    "Zelda": 1,
    "Padre": 2,
    "Balazos": 1,
    "Físico": 1,
    "Zodiacal": 1,
    "Bancaria": 1,
    "Christian": 3,
    "Saben": 1,
    "Evitar": 1,
    "Luego": 2,
    "Beca": 1,
    "Huariques": 1,
    "Papá": 1,
    "Hijo": 1,
    "Poseído": 1,
    "Santiago": 1,
    "Doña": 1,
    "Brunch": 1,
    "Ethel": 1,
    "Prohibir": 1,
    "Queen": 1,
    "Frío": 1,
    "Malas": 1,
    "Calvos": 1,
    "Amor": 3,
    "Thriller": 1,
    "Militar": 1,
    "Beso": 1,
    "Canales": 1,
    "Premios": 2,
    "Alejandro": 1,
    "Buen": 2,
    "Explota": 1,
    "Cachina": 1,
    "Camiseta": 1,
    "Soberano": 1,
    "Edición": 1,
    "Deliciosas": 1,
    "Ayudado": 1,
    "Electrónico": 3,
    "Dice": 1,
    "Ormeño": 1,
    "Cita": 1,
    "Moto": 1,
    "Bebita": 1,
    "Trepanaciones": 1,
    "Chama": 1,
    "Integral": 1,
    "Mientras": 1,
    "Bombardero": 1,
    "Entérate": 1,
    "Combatir": 1,
    "América": 4,
    "Saca": 1,
    "Signo": 1,
    "Issabela": 1,
    "Shirley": 1,
    "Youtube": 1,
    "Ganar": 2,
    "Deben": 1,
    "Volvió": 1,
    "Jueves": 1,
    "Temple": 1,
    "Uchulú": 1,
    "Retiro": 3,
    "Depara": 1,
    "Críticas": 1,
    "Boleto": 1,
    "Pitbull": 1,
    "Casi": 1,
    "García": 1,
    "Avanzado": 2,
    "Cartillas": 1,
    "Tiempo": 1,
    "Messi": 1,
    "Expareja": 2,
    "Vacunarán": 1,
    "Fecha": 1,
    "Oficios": 1,
    "Lado": 1,
    "Depositarán": 1,
    "Resultados": 1,
    "Tejer": 1,
    "Mostrar": 1,
    "Chibolín": 1,
    "Indisciplinado": 1,
    "Viajar": 2,
    "Pruebas": 1,
    "Aluminio": 1,
    "Infiel": 1,
    "Generación": 1,
    "Contundente": 1,
    "Temporada": 1,
    "Sur": 1,
    "Eliminó": 1,
    "Rigen": 1,
    "Boda": 1,
    "Responden": 1,
    "Gordos": 1,
    "Unido": 1,
    "Martins": 1,
    "Peta": 1,
    "Cuándo": 3,
    "Secuela": 1,
    "Esperada": 1,
    "Hará": 1,
    "Reunión": 1,
    "Recetas": 1,
    "Comparar": 1,
    "Covid": 3,
    "Cirujano": 1,
    "Entorno": 1,
    "Animado": 1,
    "Alondra": 1,
    "Ezio": 1,
    "Trump": 1,
    "Empezaría": 1,
    "Desayuno": 1,
    "Relato": 1,
    "Estafarla": 1,
    "Cuentas": 1,
    "Psicológico": 1,
    "Limpiar": 1,
    "Fiesta": 1,
    "Parodi": 1,
    "Migraciones": 1,
    "Anunció": 1,
    "Santos": 1,
    "Laurita": 1,
    "Núñez": 1,
    "Drag": 1,
    "Finaliza": 1,
    "Espera": 1,
    "Importante": 1,
    "Portan": 1,
    "Tolerancia": 1,
    "Golazo": 1,
    "Guillermo": 1,
    "Conquistar": 1,
    "Horrible": 1,
    "Contabilizadas": 1,
    "Burlamaqui": 1,
    "Extrema": 1,
    "Online": 1,
    "Vivió": 1,
    "Puedes": 2,
    "Jennifer": 2,
    "Adultos": 1,
    "Modo": 1,
    "Tercera": 1,
    "Grabaciones": 1,
    "Alessandro": 1,
    "Ayer": 1,
    "Confiesa": 1,
    "Hombre": 2,
    "Embarazo": 2,
    "Futbolistas": 1,
    "Gana": 1,
    "Justo": 1,
    "Paolo": 2,
    "Escándalos": 1,
    "Schwarz": 1,
    "Subsidio": 1,
    "Vacunas": 1,
    "Netflix": 2,
    "Torneo": 1,
    "Canal": 2,
    "Andahuaylas": 1,
    "Final": 2,
    "Respuesta": 1,
    "Actas": 1,
    "Salió": 2,
    "Europeos": 1,
    "Importantes": 1,
    "Enano": 1,
    "Tité": 1,
    "Soles": 1,
    "Respetar": 1,
    "Gianluca": 2,
    "Brasil": 4,
    "Martín": 1,
    "Perdonarlo": 1,
    "Usar": 1,
    "Pasar": 1,
    "Viernes": 1,
    "Lapadula": 3,
    "Homenaje": 1,
    "Realidad": 1,
    "Vacunación": 1,
    "Privacidad": 1,
    "Restricciones": 1,
    "Michelle": 2,
    "Madre": 1,
    "Países": 2,
    "Filtración": 1,
    "Quiero": 1,
    "Obtiene": 1,
    "Cree": 1,
    "Affleck": 1,
    "España": 2,
    "Solos": 1,
    "Emprendedor": 1,
    "Flor": 1,
    "Conductas": 1,
    "Confirma": 1,
    "Memes": 1,
    "Saber": 1,
    "Ben": 1,
    "Rey": 1,
    "Directo": 1,
    "Dejar": 1,
    "Unidad": 1,
    "Coreano": 1,
    "Legend": 1,
    "Guapo": 1,
    "Pueden": 1,
    "Comunitarias": 1,
    "Recordar": 1,
    "Roba": 1,
    "Envía": 1,
    "Así": 1,
    "Chapa": 1,
    "Doble": 1,
    "Separó": 1,
    "Solo": 1,
    "Migrante": 1,
    "Depósito": 1,
    "Señora": 1,
    "Tarapoto": 1,
    "País": 1,
    "Oliva": 1,
    "Reveló": 2,
    "Ver": 2,
    "Según": 1,
    "Presentó": 1,
    "Hora": 2,
    "Sufrió": 1,
    "Cristiano": 1,
    "Nueva": 3,
    "Arredondo": 1,
    "Foto": 1,
    "Joe": 1,
    "Laura": 1,
    "Asistente": 1,
    "Ozuna": 1,
    "Remedios": 1,
    "Barcelona": 1,
    "Analiza": 1,
    "Prevenirlo": 1,
    "Recibió": 1,
    "Rinde": 1,
    "Nintendo": 1,
    "Pasaporte": 3,
    "Tiktok": 1,
    "Inició": 1,
    "Manda": 1,
    "Craneanas": 1,
    "Vive": 1,
    "Kate": 1,
    "Detalles": 1,
    "Ollas": 1,
    "Quiénes": 1,
    "Bahía": 1,
    "Conmebol": 1,
    "Quiebra": 1,
    "Predicciones": 1,
    "Bono": 1,
    "Abandona": 1,
    "Vivo": 2,
    "Vih": 1,
    "Conoce": 2,
    "Denunciar": 1,
    "Disfrutar": 1,
    "Sensible": 1,
    "Dónde": 3,
    "Ente": 1,
    "Valencia": 3,
    "Apasionado": 1,
    "Matrimonio": 1,
    "Coche": 1,
    "Feminicidio": 1,
    "Invitó": 1,
    "Cambió": 1,
    "Mike": 1,
    "Bingo": 1,
    "Unidos": 1,
    "Peluchín": 2,
    "Dejarla": 1,
    "Onpe": 1,
    "Torres": 1,
    "Queden": 1,
    "Enseñan": 1,
    "Retirar": 1,
    "Gareca": 2,
    "Mejores": 2,
    "Ley": 1,
    "Wechat": 1,
    "Corazón": 1,
    "Link": 1,
    "Parte": 1,
    "Clave": 1,
    "Callao": 1,
    "Lista": 1,
    "Perros": 1,
    "Terminan": 1,
    "Voz": 2,
    "Ataque": 1,
    "Presentado": 1,
    "Defendió": 1,
    "Google": 1,
    "Amigos": 1,
    "Realizaba": 1,
    "Visa": 1,
    "Palo": 1,
    "Domingo": 1,
    "Pecho": 1,
    "Dni": 3,
    "Retama": 1,
    "Dávila": 1,
    "Familiares": 1,
    "Moleculares": 1,
    "Llena": 1,
    "Armani": 1,
    "Aún": 1,
    "Gonzalo": 1,
    "Salas": 1,
    "Historia": 3,
    "Realizan": 1,
    "Pide": 1,
    "Llegaría": 1,
    "Romeo": 1,
    "Prevenir": 1,
    "Serie": 2,
    "Choca": 1,
    "Luis": 2,
    "Heridos": 1,
    "Personas": 1,
    "Intentaban": 1,
    "Crearon": 2,
    "Annabel": 1,
    "Chanfainita": 1,
    "Patronal": 1,
    "Pato": 1,
    "Policía": 1,
    "Parejas": 1,
    "Hija": 1,
    "Gran": 1,
    "Caseros": 1,
    "Debes": 1,
    "John": 1,
    "Promotoras": 1,
    "Día": 4,
    "Redes": 1,
    "Mata": 1,
    "Castillo": 2,
    "Artista": 1,
    "José": 1,
    "Doodle": 1,
    "Ficción": 1,
    "Defiende": 1,
    "Mete": 1,
    "Jlo": 1,
    "Lopez": 1,
    "Después": 1,
    "Hermano": 1,
    "Mujer": 2,
    "Emotiva": 1,
    "Solidario": 1,
    "Llegará": 1,
    "Recibirá": 1,
    "Atlas": 1,
    "Relucientes": 1,
    "Peruano": 1,
    "Silvio": 2,
    "Deja": 1,
    "Kelvin": 1,
    "Entrenó": 1,
    "Reina": 1,
    "Previsionales": 1,
    "Colombia": 1,
    "Bomba": 1,
    "Persigue": 1,
    "Relación": 1,
    "Pedro": 2,
    "Pierda": 1,
    "Premio": 1,
    "Real": 1,
    "Sábado": 1,
    "Histórico": 1,
    "Palomino": 1,
    "Soberanos": 1,
    "Aprender": 1,
    "Delincuentes": 1,
    "Ciencia": 1,
    "Cobrar": 1,
    "Ahora": 1,
    "Juergueó": 1,
    "Ronaldo": 1,
    "Keiko": 1,
    "Fujimori": 1,
    "Sacar": 1,
    "Aquí": 1,
    "Cevichería": 1,
    "Dijo": 1,
    "Camil": 1,
    "Perú": 6,
    "Registrar": 1,
    "Lima": 1,
    "Solicitud": 2,
    "Contagio": 1,
    "Felicita": 1,
    "Construcción": 1
  },
  "correo": {
    "Paolo": 2,
    "López": 3,
    "Instagram": 1,
    "Sheyla": 1,
    "Ezio": 1,
    "Ostentar": 1,
    "Cola": 1,
    "Brasil": 5,
    "Pasajeros": 1,
    "Pendientes": 1,
    "Pedidos": 1,
    "Manchas": 1,
    "Danilo": 1,
    "Carmen": 1,
    "Soldado": 1,
    "Insta": 1,
    "Duelo": 1,
    "Observadas": 1,
    "Marcha": 1,
    "Mantener": 1,
    "Según": 1,
    "Cuarto": 1,
    "Prefirió": 1,
    "Mujer": 1,
    "Vélez": 1,
    "Dictan": 1,
    "Postulará": 1,
    "Ataque": 1,
    "Portugal": 1,
    "Hija": 1,
    "Hacia": 2,
    "Campaña": 1,
    "Torneo": 1,
    "Investiga": 1,
    "Día": 3,
    "Lápiz": 1,
    "Rafael": 1,
    "Motivador": 1,
    "Entrenamiento": 1,
    "Cada": 1,
    "Pedir": 1,
    "Gianluca": 2,
    "Publica": 1,
    "Ganar": 1,
    "Maridajes": 1,
    "Prisión": 1,
    "Mundo": 1,
    "Liberalismo": 1,
    "Provincias": 1,
    "Especial": 1,
    "Seguirme": 1,
    "Celebrar": 2,
    "Responder": 1,
    "Gustará": 1,
    "Nuevas": 1,
    "Unen": 1,
    "Seis": 1,
    "Rio": 1,
    "Respetar": 2,
    "Suma": 1,
    "Reencuentra": 1,
    "Aumento": 1,
    "Persona": 1,
    "Dos": 1,
    "Ofrecen": 1,
    "Regreso": 1,
    "Responsables": 1,
    "Sorpresa": 1,
    "Café": 1,
    "Viaje": 1,
    "Guerrero": 2,
    "Ocasionar": 1,
    "Casar": 1,
    "Casa": 3,
    "Joe": 1,
    "Oliva": 1,
    "Miguel": 1,
    "Consecutivo": 1,
    "Diarias": 1,
    "Amenacen": 1,
    "Falta": 2,
    "Sueño": 1,
    "Injusto": 1,
    "Actas": 4,
    "Ciudad": 1,
    "Récord": 1,
    "Minsa": 1,
    "Cambio": 1,
    "Nivel": 1,
    "Práctica": 1,
    "James": 1,
    "Pepera": 1,
    "Contagios": 1,
    "Sostuvo": 1,
    "Cueva": 3,
    "Ricardo": 2,
    "Romance": 1,
    "Cinco": 1,
    "Koeman": 1,
    "Resultados": 4,
    "Cotiza": 1,
    "Beto": 1,
    "Divorcio": 1,
    "Kylie": 1,
    "Voto": 1,
    "Decretan": 1,
    "Barcelona": 2,
    "Afp": 2,
    "Consejo": 1,
    "Pierde": 1,
    "Pelona": 1,
    "Confirmó": 1,
    "Nominadas": 1,
    "Horas": 2,
    "Pedro": 5,
    "Pensemos": 1,
    "Triunfo": 1,
    "Ronaldo": 3,
    "Terna": 1,
    "Tribunal": 1,
    "Segundo": 1,
    "Vuelta": 3,
    "Premier": 1,
    "Puedes": 2,
    "Serie": 1,
    "Junio": 4,
    "Camisea": 1,
    "Nulidad": 2,
    "Rebelan": 1,
    "Vizcarra": 1,
    "Suministro": 1,
    "Martín": 1,
    "Acusada": 1,
    "Ginebra": 1,
    "Dice": 2,
    "Captado": 1,
    "Cuesta": 1,
    "Categoría": 1,
    "Scarface": 1,
    "Evaluar": 1,
    "Astronautas": 1,
    "Constitucional": 1,
    "Piñata": 1,
    "Viajar": 1,
    "Excluye": 1,
    "Arriba": 2,
    "Policía": 1,
    "Keiko": 4,
    "Detenido": 1,
    "Doce": 1,
    "Haití": 1,
    "Enfocado": 1,
    "Sólida": 1,
    "Comisión": 1,
    "Hostilidad": 1,
    "Frente": 1,
    "Deliberadamente": 1,
    "Schwarz": 1,
    "Afuera": 1,
    "Léon": 1,
    "Perú": 5,
    "Preventiva": 1,
    "Mejorar": 1,
    "Putin": 3,
    "Elige": 1,
    "Nuevo": 3,
    "Rumores": 1,
    "Millones": 1,
    "Apelaciones": 3,
    "Medios": 1,
    "Dólar": 1,
    "Confía": 2,
    "Tipo": 1,
    "Racismo": 1,
    "Nicarag": 1,
    "Número": 1,
    "Peritaje": 1,
    "Muerte": 1,
    "Derbez": 1,
    "Respuesta": 1,
    "Lima": 2,
    "Amigos": 1,
    "Juntos": 1,
    "Signo": 1,
    "Supera": 1,
    "Recompensa": 1,
    "Goles": 1,
    "Alexandra": 1,
    "Eliminatorias": 1,
    "Noche": 1,
    "Méndez": 1,
    "Famoso": 1,
    "Blooper": 1,
    "Huancavelica": 1,
    "Llegar": 1,
    "Nación": 1,
    "Riesgo": 1,
    "Termina": 2,
    "José": 1,
    "Camil": 1,
    "Luis": 1,
    "Relucientes": 1,
    "Gobierno": 1,
    "Memphis": 1,
    "Aparición": 1,
    "Bomba": 2,
    "Candidatos": 1,
    "Daniela": 1,
    "Pública": 1,
    "Karen": 1,
    "Jugar": 1,
    "Debemos": 1,
    "Cateriano": 1,
    "Volverá": 1,
    "Iniciará": 1,
    "Gran": 1,
    "Kenia": 1,
    "Repita": 1,
    "Atentado": 2,
    "Intervención": 1,
    "Proclamará": 1,
    "Foto": 1,
    "Región": 1,
    "Atribuido": 1,
    "Daría": 1,
    "Mensajes": 1,
    "Darcourt": 1,
    "Mejor": 1,
    "Vacunación": 1,
    "Christian": 2,
    "Rennán": 1,
    "Compartió": 1,
    "Contabilizadas": 1,
    "Cumplió": 1,
    "Juventud": 1,
    "Onpe": 1,
    "Alcaldía": 1,
    "Burradas": 1,
    "Coche": 2,
    "Castillo": 4,
    "Arquero": 1,
    "Fujimori": 4,
    "Emitió": 1,
    "Brasileños": 1,
    "Militar": 1,
    "Reaparece": 1,
    "Dueño": 1,
    "Siguiente": 1,
    "Metropolitana": 1,
    "Concacaf": 1,
    "Fuerza": 1,
    "Revertir": 1,
    "América": 1,
    "Doble": 1,
    "Coronavirus": 2,
    "Muere": 1,
    "Gareca": 2,
    "Selección": 4,
    "Mensaje": 1,
    "Públicas": 1,
    "Voceados": 1,
    "Terrible": 1,
    "Variante": 1,
    "Opositor": 1,
    "Buen": 1,
    "Coca": 1,
    "Aún": 1,
    "Cambiado": 1,
    "Caminan": 1,
    "Madre": 2,
    "Buscan": 1,
    "Moscú": 1,
    "Previo": 1,
    "Hora": 1,
    "Miércoles": 2,
    "Toque": 1,
    "Polémica": 1,
    "Extremo": 1,
    "Precio": 1,
    "Candidato": 1,
    "Separación": 1,
    "Caso": 2,
    "Eei": 1,
    "Issabela": 1,
    "Diálogo": 1,
    "Renunciar": 1,
    "Reconciliación": 1,
    "Mamá": 1,
    "Cristiano": 4,
    "Yahaira": 1,
    "Guillermo": 1,
    "Israel": 1,
    "Modelo": 1,
    "Eléctrico": 1,
    "Anciana": 1,
    "Horóscopo": 1,
    "Aliaga": 1,
    "Pregunta": 1,
    "Entrar": 1,
    "Pisco": 1,
    "Protestas": 1,
    "Confirma": 1,
    "Caras": 1,
    "Fichar": 1,
    "Chama": 2,
    "México": 3,
    "Dosis": 1,
    "Obligatoria": 1,
    "Hijos": 1,
    "Increíble": 1,
    "Dando": 1,
    "Lenguado": 1,
    "Ochmann": 1,
    "Resalta": 1,
    "Cuidado": 1,
    "Tensa": 1,
    "Scott": 1,
    "Salas": 1,
    "Organizar": 1,
    "Besó": 1,
    "Navalny": 1,
    "Queda": 1,
    "Travis": 1,
    "Reaparecen": 1,
    "Volcadura": 1,
    "Sucesor": 1,
    "Resolver": 1,
    "Premios": 1,
    "Kylian": 1,
    "Posible": 2,
    "Embarazo": 1,
    "Misma": 1,
    "Dictadura": 1,
    "Pese": 1,
    "Presentadas": 1,
    "Tranquilita": 1,
    "Roza": 1,
    "Ser": 2,
    "Informan": 1,
    "Yturbe": 1,
    "Dávila": 1,
    "Joao": 1,
    "Mourinho": 1,
    "Autos": 1,
    "Cancelo": 1,
    "Quería": 1,
    "Popular": 2,
    "Economía": 1,
    "Quiero": 1,
    "Compañeros": 1,
    "Junto": 1,
    "Ropa": 1,
    "Quitar": 1,
    "Defiende": 1,
    "Arbitral": 1,
    "Recibe": 1,
    "Tite": 1,
    "Faustino": 1,
    "Arequipa": 1,
    "Michelle": 1,
    "Jorge": 1,
    "Rodrigo": 1,
    "Ideas": 1,
    "Cumbre": 1,
    "Reunión": 2,
    "Aluminio": 1,
    "Claves": 1,
    "Cuenta": 1,
    "Demócratas": 1,
    "Hoy": 2,
    "Seguridad": 1,
    "Quiso": 1,
    "Anular": 1,
    "Voluntad": 1,
    "Briceño": 1,
    "Señala": 1,
    "Dni": 2,
    "Ollas": 1,
    "Encuentran": 1,
    "Muertes": 2,
    "Eln": 1,
    "Libre": 1,
    "Zodiacal": 1,
    "Ivana": 1,
    "Avanzado": 1,
    "Papá": 1,
    "Aislinn": 1,
    "Tips": 2,
    "Comparación": 1,
    "Clubes": 1,
    "Retiro": 2,
    "Mbappé": 1,
    "Silva": 2,
    "Albañil": 1,
    "Pidió": 1,
    "Mauricio": 1,
    "Concurso": 1,
    "Padre": 2,
    "Servidores": 1,
    "Llamó": 1,
    "Elecciones": 4,
    "Depay": 1,
    "Atacando": 1,
    "Dejó": 1,
    "Pagar": 1,
    "Querer": 1,
    "Ciudadanos": 1,
    "Destruye": 1,
    "Municipalidad": 1,
    "Solicitud": 2,
    "Voz": 1,
    "Delincuencia": 1,
    "Detalles": 1,
    "Importante": 1,
    "Permite": 1,
    "Calificó": 1,
    "Mil": 1,
    "Participante": 1,
    "Avivan": 1,
    "Susy": 1,
    "Asprilla": 1,
    "Biden": 2,
    "Casi": 1,
    "Vez": 1,
    "Iniciado": 1,
    "Metro": 1,
    "Contabilizarse": 1,
    "Autoridades": 1,
    "Ven": 1,
    "Dejar": 2,
    "Jne": 4,
    "Anuncia": 1,
    "Manifestaciones": 1,
    "Deja": 2,
    "Mira": 1,
    "Rojas": 1,
    "Espinoza": 1,
    "Messi": 1,
    "Cbf": 1,
    "Heridos": 1,
    "Peruana": 1,
    "Peruanos": 1,
    "Preguntan": 1,
    "Colombia": 4,
    "Desopilante": 1,
    "Embajadores": 1,
    "Plasencia": 1,
    "González": 1,
    "Lujo": 1,
    "Puede": 1,
    "Whisky": 1,
    "Acciones": 1,
    "Pandemia": 2,
    "Lapadula": 2,
    "Pamela": 2,
    "Advierte": 1,
    "Covid": 3,
    "Tranquilidad": 1,
    "Van": 1,
    "Rechazo": 1,
    "Económico": 1,
    "Bernardo": 1,
    "Faltan": 1,
    "Tío": 1,
    "Díaz": 1,
    "Unidad": 1,
    "Tiempo": 2,
    "Amedrentar": 1,
    "Partido": 1,
    "India": 1,
    "Abajo": 2,
    "Segunda": 5,
    "Internacionales": 1,
    "Convocado": 1,
    "Copa": 1,
    "Jenner": 1,
    "Anunciar": 1,
    "Rodríguez": 2,
    "Hombre": 1,
    "Viviendas": 1,
    "Vladimir": 1,
    "Ense": 1,
    "Así": 3,
    "Identificación": 1,
    "Predicciones": 1,
    "Estadio": 1,
    "Enviar": 2,
    "Detectado": 1,
    "Bus": 1,
    "Críticas": 1,
    "Tragedia": 1,
    "Rechazó": 2,
    "Mueren": 1,
    "Dólares": 2,
    "Evaluación": 1,
    "Callao": 1
  },
  "gestion": {
    "Cita": 1,
    "Aplicación": 1,
    "Laboral": 1,
    "Comunista": 1,
    "Tramitar": 1,
    "Electoral": 3,
    "Ocupación": 1,
    "Oficinas": 1,
    "Mayor": 1,
    "Pedro": 1,
    "Iniciará": 1,
    "Financieros": 2,
    "Delta": 1,
    "Arequipa": 1,
    "Comisión": 1,
    "Final": 1,
    "Parejo": 1,
    "Apunta": 2,
    "Impuesto": 2,
    "Sino": 1,
    "Plan": 1,
    "Centro": 1,
    "Auge": 1,
    "Masivo": 1,
    "Avalancha": 1,
    "Diseñar": 1,
    "Buds": 1,
    "Activismo": 1,
    "Quiere": 1,
    "Apps": 1,
    "Dejó": 1,
    "Conteo": 1,
    "Peor": 1,
    "Izquierda": 1,
    "Hotel": 1,
    "Cerró": 1,
    "Ecosistema": 1,
    "Constitución": 1,
    "Wide": 1,
    "Tercera": 1,
    "Deudas": 1,
    "Entregaría": 1,
    "Canadiense": 1,
    "Junín": 1,
    "Nuevas": 1,
    "Mayo": 2,
    "Descuentos": 1,
    "Cafeterías": 1,
    "Fiel": 1,
    "Studio": 1,
    "Comportando": 1,
    "Provocará": 1,
    "Hábitos": 1,
    "Desconcierto": 1,
    "Debate": 1,
    "Electo": 1,
    "Consumo": 1,
    "Ambiental": 1,
    "Cuenta": 1,
    "Cercana": 1,
    "Corto": 1,
    "Esperar": 1,
    "Momento": 1,
    "Perú": 5,
    "Pasó": 2,
    "Padre": 3,
    "Pandemia": 1,
    "Covid": 3,
    "Propósitos": 1,
    "Salas": 1,
    "Nuevo": 2,
    "Inflación": 1,
    "Trasmisiones": 1,
    "Cambio": 1,
    "Aumentar": 1,
    "Caso": 1,
    "Crecimiento": 1,
    "Contexto": 1,
    "Implica": 1,
    "Fondo": 1,
    "Negociación": 1,
    "Desarrollo": 1,
    "Hizo": 1,
    "Orgánico": 1,
    "Open": 1,
    "Puede": 1,
    "Deterioro": 1,
    "Escenario": 1,
    "Predecible": 1,
    "Comprar": 2,
    "Todavía": 1,
    "Código": 1,
    "Odiado": 1,
    "Iniciar": 1,
    "Bonos": 1,
    "Siga": 1,
    "Coca": 1,
    "Web": 1,
    "Julio": 1,
    "Ica": 1,
    "Inmobiliaria": 1,
    "Detecta": 1,
    "Sabe": 1,
    "Presentadas": 1,
    "Laborales": 1,
    "Económicos": 1,
    "Fujimori": 1,
    "Obtener": 1,
    "Bancos": 1,
    "Empleados": 1,
    "Desgarrada": 1,
    "Camiones": 1,
    "Cerraron": 1,
    "Caja": 1,
    "Recursos": 1,
    "Servicios": 2,
    "Gobierno": 4,
    "Economía": 2,
    "Unidades": 1,
    "Global": 2,
    "Minera": 2,
    "Responsabilidad": 1,
    "Casi": 1,
    "Impulsar": 1,
    "Cancelar": 1,
    "Reforestan": 1,
    "Aprovecha": 1,
    "Protegen": 1,
    "Resultado": 1,
    "Solo": 1,
    "Fusiones": 1,
    "Probable": 1,
    "Zonas": 1,
    "Resultados": 1,
    "Afp": 2,
    "Electrónico": 1,
    "Brasil": 2,
    "Opciones": 1,
    "Cine": 1,
    "Gaming": 1,
    "Idea": 1,
    "Paltas": 1,
    "Pasos": 1,
    "Espiral": 1,
    "Falta": 1,
    "Cuatro": 1,
    "Poder": 1,
    "Exterior": 1,
    "Trabajan": 1,
    "Transforma": 1,
    "Grau": 1,
    "Corporativo": 1,
    "Aprueba": 2,
    "Metals": 1,
    "Cifra": 1,
    "Cola": 1,
    "Notebooks": 1,
    "Préstamos": 1,
    "Callao": 1,
    "Rechazó": 1,
    "Pendientes": 1,
    "Hoy": 2,
    "Paradojas": 1,
    "India": 2,
    "Estrategias": 2,
    "Pedidos": 1,
    "Oportunidad": 1,
    "Capital": 2,
    "Acertadas": 1,
    "Segunda": 2,
    "Evalúan": 1,
    "Empresas": 2,
    "Apelaciones": 2,
    "Beats": 1,
    "Corea": 1,
    "Emprendimiento": 1,
    "Mortalidad": 1,
    "Norte": 1,
    "Libertad": 1,
    "Dólar": 1,
    "Segundo": 1,
    "Toque": 1,
    "Político": 2,
    "Cristiano": 1,
    "Bolsa": 2,
    "Portada": 1,
    "Considera": 1,
    "Tambopata": 1,
    "Digital": 3,
    "Estrena": 1,
    "Digitales": 2,
    "Claves": 1,
    "Morgan": 1,
    "Stanley": 1,
    "Registrar": 1,
    "Propia": 1,
    "Ilegal": 2,
    "Regalos": 1,
    "Tiempo": 1,
    "Tecno": 1,
    "Android": 1,
    "Eléctricos": 1,
    "Biden": 1,
    "Argentinos": 1,
    "Marcas": 2,
    "Moda": 1,
    "Gobiernos": 1,
    "Duplicarse": 2,
    "Campaña": 1,
    "Vacunas": 1,
    "Private": 1,
    "Empaques": 1,
    "Oro": 1,
    "Inflacionaria": 1,
    "Gestión": 4,
    "Mandarinas": 1,
    "Presidente": 1,
    "Nulidades": 1,
    "Tipo": 1,
    "Mejoran": 1,
    "Jubilación": 1,
    "Valores": 1,
    "Colaboradores": 1,
    "Interés": 1,
    "Francke": 1,
    "Mirando": 1,
    "Vuelta": 2,
    "Minsa": 2,
    "Agroexportadoras": 1,
    "Problema": 1,
    "Aumento": 1,
    "Reafirma": 1,
    "Portafolio": 1,
    "Conozca": 1,
    "Recupera": 1,
    "Exportación": 1,
    "Decisiones": 1,
    "Agroexportaciones": 1,
    "Plazo": 1,
    "Volatilidad": 1,
    "Dos": 1,
    "Proclamará": 1,
    "Música": 1,
    "Dice": 1,
    "Posicionar": 1,
    "Hipotecario": 1,
    "Campeón": 1,
    "Copa": 1,
    "Costo": 1,
    "Vender": 1,
    "Visión": 1,
    "Iniciativa": 1,
    "Semana": 1,
    "Propiedad": 1,
    "Peruanos": 2,
    "Reserva": 1,
    "Indicadores": 2,
    "Presupuesto": 1,
    "Impulsan": 2,
    "Cae": 1,
    "Mitos": 1,
    "Producción": 2,
    "Intelectual": 1,
    "Cinco": 1,
    "Socialista": 1,
    "Peruano": 2,
    "Riesgo": 2,
    "Huéspedes": 1,
    "Liga": 1,
    "Compradas": 1,
    "Modelo": 1,
    "Espárragos": 1,
    "Efecto": 1,
    "Mejores": 1,
    "Obtiene": 1,
    "Día": 5,
    "Alto": 1,
    "Galerías": 1,
    "Credicorp": 1,
    "Westin": 1,
    "Putin": 1,
    "Tributación": 1,
    "Onpe": 1,
    "Fondos": 4,
    "Profesionales": 1,
    "Fintech": 1,
    "Original": 1,
    "Mesa": 1,
    "Ositran": 1,
    "Colecta": 1,
    "Gestora": 1,
    "Tres": 4,
    "Retos": 2,
    "Menores": 1,
    "Reunión": 1,
    "Analistas": 1,
    "Mercados": 3,
    "Casa": 1,
    "Manera": 1,
    "Pamolsa": 1,
    "Azúcar": 1,
    "Permiso": 1,
    "Abiertas": 1,
    "Descarta": 1,
    "Transitoria": 1,
    "Capeco": 1,
    "Baja": 1,
    "Abrieron": 1,
    "Medioambiental": 1,
    "Junio": 3,
    "Permanencia": 1,
    "Muelle": 1,
    "Fallecimientos": 1,
    "Bodegas": 1,
    "Hacer": 1,
    "Institucionalidad": 1,
    "Duplicará": 1,
    "Inversión": 1,
    "Hacia": 1,
    "Nueva": 1,
    "Puntos": 1,
    "Sector": 1,
    "Revise": 1,
    "Autos": 1,
    "Intolerancia": 1,
    "Tener": 1,
    "Variante": 2,
    "Realidad": 1,
    "Queda": 1,
    "América": 1,
    "Paternidad": 1,
    "Buscan": 1,
    "Management": 1,
    "Blogs": 1,
    "Luego": 2,
    "Ideas": 1,
    "Subastarán": 1,
    "Mercado": 2,
    "Advierte": 1,
    "Castillo": 2,
    "Dinero": 1,
    "Absurda": 1,
    "Cáncer": 1,
    "Alza": 1,
    "Mínimo": 1,
    "Extra": 1,
    "Razón": 1,
    "Airpods": 1,
    "Marca": 1,
    "Operan": 1,
    "Equity": 1,
    "Podría": 1,
    "Rusia": 1,
    "Sur": 1,
    "Proclamado": 1,
    "Yauricocha": 1,
    "Lima": 3,
    "Afectadas": 1,
    "Venture": 1,
    "Sandbox": 1,
    "Perder": 1,
    "Batería": 1,
    "Economist": 1,
    "Financiero": 1,
    "Plus": 1,
    "Movimiento": 1,
    "Dólares": 1,
    "Ola": 1,
    "Tarifas": 1,
    "Seis": 1,
    "Eficiente": 1,
    "Lunes": 1,
    "Triángulo": 1,
    "Casos": 1,
    "Negocio": 1,
    "Apuntan": 1,
    "Pide": 1,
    "Nación": 1,
    "Replantea": 1,
    "Factores": 1,
    "Hongo": 1,
    "Asegurar": 1,
    "Suscriptor": 1,
    "Clave": 1,
    "Papá": 1,
    "Ayuda": 1,
    "Resolver": 1,
    "Extranjeros": 1,
    "Beneficiará": 1,
    "Acciones": 1,
    "World": 1,
    "Anticipada": 1,
    "Región": 1,
    "Licencia": 1,
    "Formalización": 1,
    "Negro": 1,
    "Apple": 1,
    "Gamarra": 1,
    "Operar": 1,
    "Liderazgo": 1,
    "Bitcóin": 1,
    "Alejan": 1,
    "Dejar": 1,
    "Cambiar": 1,
    "Futuro": 1,
    "Retirarían": 1,
    "Piso": 1,
    "Mina": 2,
    "Jne": 4,
    "Celulares": 1,
    "Café": 1,
    "Tareas": 1,
    "Operaciones": 1,
    "Moquegua": 1,
    "Reduciendo": 1,
    "Pasaporte": 1,
    "Minería": 2,
    "Comprador": 1,
    "Pensiones": 1,
    "País": 1,
    "Palabra": 1,
    "Inmueble": 1,
    "Club": 2,
    "Den": 1,
    "Adquisiciones": 1,
    "Diez": 1,
    "Afiliados": 1,
    "Irregularidades": 1,
    "Amigables": 1,
    "Sierra": 1,
    "Eco": 1,
    "Apoyar": 1,
    "Millones": 3,
    "Libre": 1,
    "Ronaldo": 1
  },
  "peru21": {
    "Alrededor": 1,
    "Cortitas": 2,
    "Gusta": 1,
    "Valcárcel": 1,
    "Plazos": 1,
    "Laura": 1,
    "Sexto": 1,
    "Fuerza": 2,
    "Popular": 1,
    "Tiempo": 1,
    "Preferencial": 1,
    "Responder": 1,
    "Quería": 1,
    "Declaraciones": 1,
    "Especial": 1,
    "Pandemia": 1,
    "Colombia": 1,
    "Ataque": 1,
    "Fujimori": 2,
    "Habeas": 1,
    "Vacunas": 1,
    "Eurocopa": 1,
    "Miembros": 1,
    "Padre": 1,
    "Presentadas": 1,
    "Karen": 1,
    "Gran": 1,
    "Videos": 1,
    "Poder": 2,
    "Dio": 1,
    "Partidos": 1,
    "Bomba": 1,
    "Cafetera": 1,
    "Centro": 2,
    "Recortar": 1,
    "Temporada": 1,
    "Preparar": 2,
    "Grados": 1,
    "Stoessel": 1,
    "Evento": 2,
    "Seguimos": 1,
    "And": 1,
    "Junín": 1,
    "Vacaciones": 1,
    "Rumores": 2,
    "Expresa": 1,
    "Privadas": 1,
    "Gianluca": 2,
    "Familia": 1,
    "Covid": 3,
    "Privado": 1,
    "Aplicarán": 1,
    "Geisha": 1,
    "Triunfar": 1,
    "Fiscal": 1,
    "Aprende": 1,
    "Julio": 2,
    "Grabaciones": 1,
    "Jugará": 1,
    "Ingeniero": 1,
    "Kim": 1,
    "Vuelta": 2,
    "Medio": 1,
    "Solo": 1,
    "Goles": 1,
    "Vigencia": 1,
    "Papeletas": 1,
    "Danilo": 1,
    "Música": 1,
    "Dos": 1,
    "Pedido": 1,
    "Copa": 3,
    "Democracia": 1,
    "Jordana": 1,
    "Paulina": 1,
    "Recibirá": 2,
    "Azul": 1,
    "Romance": 1,
    "Elecciones": 1,
    "Solidaridad": 1,
    "Faustino": 1,
    "Metropolitano": 1,
    "Alborada": 1,
    "Castillo": 2,
    "Especialidad": 2,
    "Premios": 2,
    "Aislinn": 2,
    "Selección": 2,
    "Burrola": 1,
    "Resolver": 2,
    "Pendientes": 1,
    "Garner": 1,
    "Nilton": 2,
    "Soles": 1,
    "Reafirman": 1,
    "Miraflores": 3,
    "Gianluigi": 1,
    "Comparar": 1,
    "Perú": 6,
    "Rápidos": 1,
    "Eléctricos": 1,
    "Furious": 1,
    "Jenner": 1,
    "Affleck": 1,
    "Miami": 2,
    "Bruce": 1,
    "Corea": 1,
    "Pablo": 1,
    "Citará": 1,
    "Acnur": 1,
    "Sencillos": 1,
    "Habla": 1,
    "Saber": 2,
    "Gourmet": 1,
    "Desembolso": 1,
    "Belinda": 1,
    "Resultados": 2,
    "Solicitar": 1,
    "Jong": 1,
    "Brewster": 1,
    "Casi": 1,
    "Mil": 1,
    "Rodríguez": 1,
    "Regirá": 1,
    "Oro": 1,
    "Tercer": 1,
    "Lapadula": 2,
    "García": 1,
    "Semana": 1,
    "Puede": 1,
    "Puedes": 1,
    "Reavivan": 1,
    "Electorales": 1,
    "Buffon": 1,
    "Juntos": 2,
    "Caso": 1,
    "Pedro": 1,
    "Todavía": 1,
    "Afp": 2,
    "Heridos": 1,
    "Atribuido": 1,
    "Ochmann": 2,
    "Kylie": 1,
    "Virtual": 1,
    "Nuevas": 1,
    "Imaginabas": 1,
    "Defender": 1,
    "Opinión": 1,
    "Juventud": 1,
    "Funcionarios": 1,
    "Universitarios": 1,
    "Separación": 1,
    "Restaurantes": 1,
    "Colega": 1,
    "Pfizer": 1,
    "Tipo": 1,
    "Serie": 1,
    "Derbez": 3,
    "Importar": 1,
    "Rita": 1,
    "Pregunta": 1,
    "Evaluará": 1,
    "Alianza": 1,
    "Martes": 1,
    "Nueva": 1,
    "Brasil": 2,
    "Celebrar": 1,
    "Sagrado": 1,
    "Producir": 1,
    "Sebastián": 1,
    "Relación": 2,
    "Schwarz": 1,
    "Rendimiento": 1,
    "Recibe": 1,
    "Declaran": 1,
    "Análisis": 1,
    "Cosas": 2,
    "Yatra": 1,
    "López": 1,
    "Adelgaza": 1,
    "Debes": 1,
    "Gareca": 2,
    "Killers": 1,
    "Dni": 1,
    "Delivery": 1,
    "Cada": 1,
    "Admisión": 1,
    "Casar": 1,
    "Chico": 1,
    "Tite": 1,
    "Joe": 1,
    "Entérate": 1,
    "Amigo": 1,
    "Código": 1,
    "Jennifer": 1,
    "Nuevo": 3,
    "Unas": 1,
    "Revela": 1,
    "Ricardo": 1,
    "Christian": 2,
    "Cermeño": 1,
    "Novela": 1,
    "Militar": 1,
    "Tarjeta": 1,
    "Tema": 2,
    "Jiu": 1,
    "Jay": 1,
    "Segunda": 2,
    "Presenta": 2,
    "Llegó": 1,
    "Caen": 1,
    "Fase": 1,
    "Tini": 1,
    "Votos": 1,
    "Edición": 2,
    "Mediocampista": 1,
    "Reconocimiento": 1,
    "Momento": 1,
    "Descartan": 1,
    "Ciclistas": 1,
    "Editorial": 2,
    "Nuevos": 1,
    "Menta": 1,
    "Desata": 1,
    "Solidario": 1,
    "Invocamos": 1,
    "Pass": 1,
    "Eln": 1,
    "Harina": 1,
    "Fast": 1,
    "Cerveza": 1,
    "Instaló": 1,
    "Hora": 1,
    "Destacó": 1,
    "Judicial": 2,
    "Potencial": 1,
    "Billboard": 1,
    "Adriana": 1,
    "Misteriosos": 1,
    "Instagram": 1,
    "Imitadora": 1,
    "Bono": 1,
    "James": 1,
    "Trufas": 1,
    "Millones": 1,
    "Falta": 1,
    "Jitsu": 1,
    "Premio": 1,
    "Junio": 2,
    "Pollo": 1,
    "Así": 2,
    "Deja": 2,
    "Perfecta": 1,
    "Separó": 1,
    "Aprobado": 1,
    "Ingresar": 1,
    "Bar": 1,
    "Procesal": 1,
    "Retiro": 3,
    "Olvida": 1,
    "Santa": 1,
    "Knockout": 1,
    "Apufest": 1,
    "Cusco": 2,
    "Prefiere": 1,
    "José": 2,
    "Anuncia": 2,
    "Ola": 1,
    "Festival": 1,
    "Trabajar": 1,
    "Sigue": 1,
    "Calificó": 1,
    "Preocupación": 1,
    "Cobrar": 1,
    "Oficiales": 1,
    "Vehículos": 1,
    "Fairytale": 1,
    "Después": 1,
    "Penal": 1,
    "Reunirse": 1,
    "Rio": 1,
    "Burradas": 1,
    "Peruano": 1,
    "Cueva": 2,
    "Dustland": 1,
    "Mensaje": 1,
    "Rosaldo": 1,
    "Multitud": 1,
    "Cafetería": 2,
    "Cheese": 1,
    "Kiwicha": 1,
    "Ugarte": 1,
    "Peruanos": 1,
    "Hub": 1,
    "Descarta": 1,
    "Motivo": 1,
    "Favor": 2,
    "Urviola": 1,
    "Chuck": 1,
    "Café": 5,
    "Dejen": 1,
    "Momentos": 1,
    "Implicados": 1,
    "Demanda": 1,
    "Estreno": 1,
    "Oliva": 1,
    "Anunciar": 1,
    "Rechazó": 1,
    "Improcedente": 1,
    "Juan": 1,
    "Tello": 1,
    "Detienen": 1,
    "Impedimento": 1,
    "Llora": 1,
    "Kate": 1,
    "Salud": 2,
    "Restaurante": 1,
    "Increíbles": 1,
    "Actualizar": 1,
    "Ginebra": 1,
    "Biden": 1,
    "Detalles": 1,
    "Brasa": 1,
    "Yucra": 1,
    "Nace": 1,
    "Ezio": 1,
    "World": 1,
    "Acuña": 1,
    "Primera": 1,
    "Torta": 1,
    "Técnica": 1,
    "Mano": 1,
    "Dígito": 1,
    "Bebida": 1,
    "Personales": 1,
    "City": 1,
    "Nodal": 1,
    "Salida": 1,
    "Cafeteros": 1,
    "Multimarca": 1,
    "Cerrón": 2,
    "Tercera": 2,
    "Puedo": 1,
    "César": 1,
    "Decisión": 1,
    "Parma": 1,
    "Empresaria": 1,
    "Ser": 1,
    "Iniciaron": 1,
    "Comienza": 1,
    "Scott": 1,
    "Latina": 1,
    "Wheeler": 1,
    "Mejor": 1,
    "Histórica": 1,
    "Coche": 1,
    "Gianfranco": 1,
    "Guzmán": 1,
    "Ecológico": 1,
    "Dosis": 1,
    "Muestra": 1,
    "Reconciliación": 1,
    "Onpe": 2,
    "Injusto": 1,
    "Quiso": 1,
    "Especulaciones": 1,
    "Dinámicos": 2,
    "Iván": 1,
    "Apelaciones": 1,
    "Papá": 1,
    "Recursos": 1,
    "Vladimir": 2,
    "Comparte": 1,
    "Mauricio": 2,
    "Paolo": 1,
    "Compromiso": 2,
    "Meses": 1,
    "Cumbre": 1,
    "Pobreza": 1,
    "Tradicional": 1,
    "Versionar": 1,
    "Vamos": 1,
    "Peruana": 2,
    "Pruebas": 1,
    "Situación": 1,
    "Libre": 1,
    "Guerrero": 1,
    "Aceptar": 1,
    "Ozuna": 1,
    "Arequipa": 1,
    "Emprendimientos": 1,
    "Estadio": 3,
    "Según": 2,
    "Debe": 1,
    "Trabajadores": 1,
    "Posible": 2,
    "Renueva": 1,
    "Hoy": 2,
    "Pamela": 1,
    "Presume": 1,
    "Plaza": 1,
    "Mañana": 1,
    "Líquido": 1,
    "Aún": 1,
    "Hablaban": 1,
    "Sur": 1,
    "Miércoles": 1,
    "Descubre": 1,
    "Cordero": 1,
    "Generación": 1,
    "Identificación": 1,
    "Unió": 1,
    "Buena": 2,
    "Consejos": 1,
    "Crear": 1,
    "Cruz": 1,
    "Cuento": 2,
    "Reina": 1,
    "Villalobos": 1,
    "Jne": 3,
    "Creo": 1,
    "Putin": 1,
    "Grupos": 1,
    "América": 3,
    "Onu": 1,
    "Tiranos": 1,
    "Luce": 1,
    "País": 2,
    "Bandera": 2,
    "Carta": 1,
    "Millón": 1,
    "Springsteen": 1,
    "Lado": 1,
    "Victoria": 1,
    "Positivo": 1,
    "Castro": 1,
    "Alessandra": 1,
    "Norte": 1,
    "Fin": 1,
    "Postres": 1,
    "Saba": 1,
    "Mensajes": 1,
    "Vuelve": 2,
    "Pasado": 1,
    "Estudiantes": 1,
    "Vicio": 1,
    "Capítulo": 1,
    "Birdz": 1,
    "Hunde": 1,
    "Sabores": 1,
    "Debut": 1,
    "Cristiano": 2,
    "Inclusión": 1,
    "Artesánico": 1,
    "Septiembre": 1,
    "Presentados": 1,
    "Incas": 1,
    "Cifras": 1,
    "Realiza": 1,
    "Campo": 1,
    "Caviar": 1,
    "Asprilla": 1,
    "Enseñar": 1,
    "Nominación": 1,
    "Aceite": 1,
    "Récord": 1,
    "Matrimonio": 1,
    "Keiko": 2,
    "Limitada": 1,
    "Soberano": 1,
    "Puruchuco": 1,
    "Ben": 1,
    "Play": 1,
    "Concepto": 1,
    "Felicita": 1,
    "Travis": 1,
    "Local": 1,
    "Portugal": 1,
    "Fechas": 1,
    "Ayuda": 1,
    "Chocolate": 1,
    "Día": 2,
    "Retomado": 1,
    "Vigente": 1,
    "Lima": 3,
    "Cajamarca": 1,
    "Unidad": 1,
    "Jlo": 1,
    "Nulidad": 1,
    "Furiosos": 1,
    "Empresas": 1,
    "Entrevista": 2,
    "Frente": 1,
    "Eugenio": 1,
    "Brinda": 1,
    "Resumen": 1,
    "Podrán": 1,
    "Darse": 1,
    "Versión": 1,
    "Corpus": 1,
    "Ronaldo": 2,
    "Pausini": 1,
    "Real": 1,
    "Obtener": 1,
    "Santos": 2,
    "Guiller": 1,
    "Congreso": 1,
    "Inteligente": 1
  },
  "expreso": {
    "Danza": 1,
    "Criminal": 2,
    "Piura": 1,
    "Fortalécelo": 1,
    "Justicia": 2,
    "Venus": 1,
    "Goleó": 1,
    "Extremistas": 1,
    "Misiones": 1,
    "Twitter": 1,
    "Políticos": 2,
    "Corvetto": 1,
    "Salinas": 1,
    "Puede": 1,
    "Juventus": 1,
    "Proclamará": 1,
    "China": 1,
    "Personas": 4,
    "Locura": 1,
    "Virtual": 1,
    "Keiko": 2,
    "Elecciones": 2,
    "Paredes": 1,
    "Whatsapp": 1,
    "Médicos": 1,
    "Rafael": 1,
    "Cáncer": 1,
    "Millennial": 1,
    "Valdez": 1,
    "Princesa": 1,
    "Europea": 1,
    "Diesel": 1,
    "Operación": 1,
    "Empató": 1,
    "Tiranuelos": 1,
    "Bacteria": 1,
    "Inversión": 1,
    "Pide": 3,
    "Mendoza": 1,
    "Mascarillas": 1,
    "Máximo": 1,
    "Extractiva": 1,
    "Resultaron": 1,
    "Premio": 2,
    "Diferencia": 1,
    "Convertido": 1,
    "Ciudadanos": 1,
    "Revolucionario": 1,
    "Medio": 1,
    "Perfecto": 1,
    "Equipo": 1,
    "Opinión": 2,
    "Alcanzaron": 1,
    "Participación": 1,
    "Susel": 1,
    "Pedro": 3,
    "Extra": 2,
    "Negro": 1,
    "Epidemiológico": 1,
    "Ingreso": 1,
    "Dejar": 1,
    "Dios": 1,
    "Normal": 1,
    "Dejaremos": 1,
    "Bermejo": 1,
    "Morado": 1,
    "Diosa": 1,
    "Cristiano": 2,
    "Francia": 1,
    "Tratamiento": 1,
    "Feminismos": 1,
    "Materia": 3,
    "Latin": 1,
    "Productiva": 1,
    "Llegamos": 1,
    "Llama": 1,
    "Troll": 1,
    "Inscripciones": 1,
    "Alimentando": 1,
    "Riesgo": 1,
    "Colombia": 1,
    "Disputar": 1,
    "Vacunación": 2,
    "Hijos": 1,
    "Local": 1,
    "Sociales": 1,
    "Alista": 1,
    "Peritajes": 1,
    "Vida": 1,
    "Traicionan": 1,
    "Ministro": 2,
    "Vuelta": 3,
    "Compras": 1,
    "Denunció": 1,
    "Ganó": 1,
    "Revista": 1,
    "Hotel": 1,
    "Sido": 1,
    "Profundo": 1,
    "Jne": 7,
    "Muñante": 1,
    "Finlandia": 1,
    "Asamblea": 1,
    "Comparecencia": 1,
    "Vraem": 1,
    "Ejército": 1,
    "Delitos": 1,
    "Convirtió": 1,
    "Legales": 1,
    "Publicidades": 1,
    "Simple": 1,
    "Guzmán": 1,
    "Eclipse": 1,
    "Quiere": 1,
    "Alcaldía": 1,
    "Asturias": 1,
    "Dólares": 3,
    "Valores": 1,
    "Problemas": 2,
    "Sitio": 1,
    "Sanidad": 1,
    "Dota": 1,
    "Mapa": 1,
    "Traicionar": 1,
    "Producirán": 1,
    "Retrasa": 1,
    "Viva": 1,
    "Titular": 1,
    "Proceso": 1,
    "Resultados": 3,
    "Protestas": 1,
    "Futurista": 1,
    "América": 4,
    "Recomendaciones": 1,
    "Democrática": 1,
    "Exigimos": 1,
    "Raras": 1,
    "Actuar": 1,
    "Plantón": 1,
    "Revolucionó": 1,
    "Relajarse": 1,
    "Solo": 1,
    "Internacional": 3,
    "Castigó": 1,
    "Mensaje": 1,
    "Violentos": 2,
    "Sabes": 1,
    "Pueden": 1,
    "Derecho": 1,
    "Urge": 1,
    "Inteligente": 1,
    "Falsas": 2,
    "Intensifican": 1,
    "Legalidad": 1,
    "Viaje": 1,
    "Exhibe": 1,
    "Avasallar": 1,
    "Leonardo": 1,
    "Parecido": 1,
    "Monos": 1,
    "Ilusa": 1,
    "Suiza": 1,
    "Libre": 1,
    "Bomba": 1,
    "Inconmensurable": 1,
    "Importancia": 1,
    "Organizará": 1,
    "Casos": 1,
    "Heladas": 1,
    "Decreto": 1,
    "Símbolo": 1,
    "Admita": 1,
    "Unirá": 1,
    "Estrena": 1,
    "Imponga": 1,
    "Casi": 1,
    "Afiebradas": 1,
    "Presenta": 1,
    "Nuria": 1,
    "Respeto": 1,
    "Arrastra": 1,
    "Prohíbe": 1,
    "Fiscalía": 3,
    "Resistencia": 1,
    "Abrigo": 1,
    "Psicoanálisis": 1,
    "Acceda": 1,
    "Luego": 2,
    "Eurocopa": 4,
    "Vacunas": 1,
    "Enero": 1,
    "Pronto": 1,
    "Habla": 1,
    "Gravis": 1,
    "Anular": 1,
    "Millones": 6,
    "Morenatti": 1,
    "Bicentenario": 1,
    "Beneficioso": 1,
    "Credencial": 1,
    "Argentina": 1,
    "Jorge": 1,
    "Callao": 1,
    "López": 1,
    "Princesas": 1,
    "Presidencial": 1,
    "Defensores": 1,
    "Récords": 1,
    "Lluvia": 1,
    "Inmobiliario": 1,
    "Nivel": 2,
    "Carta": 2,
    "Espacial": 1,
    "Segunda": 4,
    "Conversatorios": 1,
    "Julio": 1,
    "Vladimir": 6,
    "Ayudar": 1,
    "Precisar": 1,
    "Minedu": 1,
    "Guillermo": 1,
    "Reprogramar": 1,
    "Llevado": 1,
    "Entrega": 1,
    "Anunció": 1,
    "Falta": 1,
    "Descartaría": 1,
    "Operativo": 1,
    "Mata": 1,
    "Fuego": 2,
    "Castrochavismo": 1,
    "Pedidos": 1,
    "Lucha": 1,
    "Estudio": 1,
    "Artificial": 1,
    "Niega": 1,
    "Cueva": 2,
    "Salida": 2,
    "Snmpe": 1,
    "Salga": 1,
    "Ruta": 1,
    "Fugan": 1,
    "Anterior": 1,
    "Sigrid": 1,
    "Actuales": 1,
    "Huérfanas": 1,
    "Marcha": 1,
    "Huawei": 1,
    "Padura": 1,
    "Tipos": 1,
    "Seis": 1,
    "Fecha": 4,
    "Ero": 1,
    "Policial": 1,
    "Privada": 1,
    "Dice": 1,
    "Contenidos": 1,
    "Investigaciones": 1,
    "Sigue": 3,
    "Luis": 1,
    "Electoral": 4,
    "Vacuna": 1,
    "Perfume": 1,
    "Pueblo": 3,
    "Enfermedades": 1,
    "Tampoco": 1,
    "Mineras": 1,
    "Aseguró": 1,
    "Dolor": 1,
    "Institucionalidad": 1,
    "Afrontar": 1,
    "Irregularidad": 1,
    "Amor": 1,
    "Bazán": 1,
    "Exportaciones": 1,
    "Sexuales": 1,
    "Regalo": 1,
    "Abril": 1,
    "Cargo": 1,
    "Ceguera": 1,
    "Propone": 1,
    "Policía": 1,
    "Seguridad": 1,
    "Diarios": 1,
    "Evaluar": 1,
    "Bukowski": 1,
    "Proclame": 2,
    "Probó": 1,
    "Italia": 1,
    "Oficialista": 1,
    "Declara": 1,
    "Nasa": 1,
    "Renunciar": 3,
    "Soto": 1,
    "Captura": 1,
    "Dea": 1,
    "Apelaciones": 1,
    "Relación": 1,
    "Llosa": 2,
    "Celebrar": 1,
    "Primer": 2,
    "Cárcel": 1,
    "Conflicto": 1,
    "Comunismo": 1,
    "Cargos": 1,
    "Bartola": 1,
    "Plata": 1,
    "Ejecuta": 1,
    "Essalud": 3,
    "Jurado": 1,
    "Economía": 2,
    "Dan": 1,
    "Cerco": 1,
    "Votación": 1,
    "Donaron": 1,
    "Recibe": 1,
    "Vacunarse": 1,
    "Cae": 1,
    "Fenómeno": 1,
    "Conteo": 1,
    "Elegido": 1,
    "Completaron": 1,
    "Equipos": 1,
    "Bolognesi": 1,
    "Raphael": 1,
    "Debe": 1,
    "Bcr": 1,
    "Alejandro": 1,
    "Proyecto": 2,
    "Inauguran": 1,
    "Valor": 1,
    "Trasciende": 1,
    "Ministerio": 2,
    "Crisis": 1,
    "Chile": 1,
    "Izquierda": 1,
    "Requiere": 1,
    "Superficie": 1,
    "Soles": 1,
    "Legitimidad": 1,
    "Emergencia": 2,
    "Lagarta": 1,
    "Contraloría": 1,
    "Perú": 11,
    "Rompe": 1,
    "Comisaria": 1,
    "Pública": 1,
    "Expreso": 3,
    "Covid": 6,
    "Native": 1,
    "Real": 2,
    "Waldo": 1,
    "Pro": 1,
    "Nueva": 1,
    "Vanya": 1,
    "Dinámicos": 2,
    "Construcción": 1,
    "Bancadas": 1,
    "Sonido": 1,
    "Adquiere": 1,
    "Saber": 1,
    "Manuel": 1,
    "Racismo": 1,
    "Conozca": 1,
    "Sagasti": 1,
    "Ayni": 1,
    "Verse": 1,
    "Verdadero": 1,
    "Emma": 1,
    "Yonhy": 1,
    "Arterial": 1,
    "Inmune": 1,
    "Peor": 1,
    "Caral": 1,
    "Patológico": 1,
    "Fraude": 1,
    "Desconocimiento": 1,
    "Dentro": 3,
    "Criminalizar": 1,
    "Hipertensión": 1,
    "Christian": 2,
    "Todas": 1,
    "Cuatro": 1,
    "Narcoterroristas": 1,
    "Verdad": 1,
    "Convocan": 1,
    "Cita": 1,
    "Organización": 2,
    "Tribeca": 1,
    "Incendiar": 1,
    "Postular": 1,
    "Recibirá": 1,
    "Expulsar": 1,
    "Emilio": 1,
    "Podamos": 1,
    "Violeta": 1,
    "Metropolitana": 1,
    "Peruanos": 1,
    "Videoarte": 1,
    "Inteligencia": 1,
    "Museo": 2,
    "Reagruparon": 1,
    "Vih": 1,
    "Rojos": 1,
    "Firmas": 2,
    "Sergio": 1,
    "Distraerá": 1,
    "Obra": 1,
    "Ley": 2,
    "Celular": 1,
    "Alto": 2,
    "Previos": 1,
    "Resolver": 1,
    "Goleador": 1,
    "Racha": 1,
    "Bermúdez": 1,
    "Fusión": 1,
    "Exigen": 1,
    "Interviene": 1,
    "Variante": 1,
    "Cúcuta": 1,
    "Denuncia": 1,
    "Conectividad": 1,
    "Miastenia": 1,
    "Diario": 1,
    "Band": 1,
    "Permanente": 1,
    "Weinstein": 1,
    "Acusaciones": 1,
    "Cola": 1,
    "Cumbre": 1,
    "Fría": 1,
    "Competir": 1,
    "Solar": 1,
    "Pulmonar": 1,
    "Club": 1,
    "Tema": 1,
    "Observadas": 1,
    "Ilusión": 1,
    "Destinará": 1,
    "Industria": 1,
    "Simpatizantes": 1,
    "Votos": 1,
    "Tomar": 1,
    "Madre": 1,
    "Triunfo": 1,
    "Según": 2,
    "Cierra": 1,
    "Vitíligo": 1,
    "Capitales": 1,
    "Lateral": 1,
    "Brasileño": 1,
    "Estación": 1,
    "Respecto": 1,
    "Dirigente": 1,
    "Esperanza": 1,
    "Sábado": 1,
    "Operaciones": 1,
    "Padre": 1,
    "Recibido": 1,
    "Dispositivos": 1,
    "Ahora": 1,
    "Fiesta": 1,
    "Imágenes": 1,
    "Cantera": 1,
    "Pillos": 1,
    "Evitar": 2,
    "Ugarte": 1,
    "Día": 3,
    "Acudieron": 1,
    "Humana": 1,
    "Ronaldo": 2,
    "Salud": 5,
    "Educación": 1,
    "Etapa": 1,
    "Hezbollah": 1,
    "Vin": 1,
    "Once": 1,
    "Enfocado": 1,
    "Pierde": 1,
    "Presidenta": 1,
    "Colegio": 1,
    "America": 1,
    "Prevención": 1,
    "Pradera": 1,
    "Interpretar": 1,
    "Finales": 1,
    "Misma": 1,
    "Catástrofe": 1,
    "Extraño": 1,
    "Voluntaria": 1,
    "Mala": 1,
    "Vacunado": 1,
    "Clasifican": 1,
    "Electorales": 1,
    "Conversatorio": 1,
    "Sector": 1,
    "Lescano": 1,
    "Elección": 1,
    "Modifica": 1,
    "Alta": 1,
    "Aprovecha": 1,
    "Teatro": 2,
    "Partió": 1,
    "Hijo": 1,
    "Venció": 2,
    "Vargas": 2,
    "Niveles": 1,
    "Caviares": 1,
    "Maduro": 1,
    "Color": 1,
    "Oportunidad": 1,
    "Pretenden": 1,
    "Pasan": 1,
    "Brigada": 1,
    "Esparch": 1,
    "Ojalá": 1,
    "Delincuentes": 1,
    "Premiado": 1,
    "Calidad": 1,
    "Privado": 1,
    "Mientras": 2,
    "Filántropa": 1,
    "Principios": 1,
    "Origen": 1,
    "Sacrificados": 1,
    "Contrario": 1,
    "Madrid": 2,
    "Merino": 1,
    "Lacan": 1,
    "Destino": 1,
    "Chocolate": 1,
    "Demorón": 1,
    "Pozo": 1,
    "Salaverry": 1,
    "Constitución": 2,
    "Brasil": 4,
    "Lagarto": 2,
    "Solicitado": 1,
    "Logra": 1,
    "Emblemática": 1,
    "Narcosenderismo": 1,
    "Hispano": 1,
    "Nicaragua": 1,
    "Historia": 1,
    "Uso": 2,
    "Regional": 1,
    "Invitados": 1,
    "Morgana": 1,
    "Gianluca": 1,
    "Constituyente": 1,
    "Tolerancia": 1,
    "Parecen": 1,
    "Debemos": 1,
    "Esfera": 1,
    "Audiencia": 1,
    "Gesto": 1,
    "Animales": 1,
    "Espera": 1,
    "Escritura": 1,
    "Popular": 1,
    "Harvey": 1,
    "Manera": 1,
    "Exdirectores": 1,
    "Hacer": 1,
    "Expertos": 1,
    "Venta": 1,
    "Cerrón": 8,
    "California": 1,
    "Golpe": 1,
    "Reuniones": 1,
    "Corporativa": 1,
    "Suscripción": 2,
    "Dosis": 1,
    "Videovigilancia": 1,
    "Yerbabuena": 1,
    "Transferencia": 1,
    "Eswachaka": 1,
    "Guerra": 1,
    "Saga": 1,
    "Boris": 1,
    "Diseñan": 1,
    "Dudas": 1,
    "Avi": 1,
    "Importante": 1,
    "Controle": 1,
    "Asuma": 1,
    "Paradoja": 1,
    "Mitad": 1,
    "Cierre": 1,
    "Conoce": 1,
    "Nuevo": 2,
    "Nulidad": 1,
    "Arte": 1,
    "Prensa": 2,
    "Científicos": 1,
    "Piel": 1,
    "Vacunar": 1,
    "Dos": 3,
    "Llegando": 1,
    "Advirtió": 1,
    "Promociones": 1,
    "Gubernamental": 1,
    "Insulta": 1,
    "Cummings": 1,
    "Unidos": 1,
    "Allana": 1,
    "Avatar": 1,
    "Universo": 1,
    "Libertad": 1,
    "Coche": 1,
    "País": 2,
    "Distraído": 1,
    "Sillar": 1,
    "Descartar": 2,
    "Festival": 3,
    "Correctamente": 1,
    "Carrera": 2,
    "Ricardo": 4,
    "Llamado": 1,
    "Cobre": 1,
    "Poder": 2,
    "Dengue": 1,
    "Urgente": 1,
    "Film": 1,
    "Jugar": 1,
    "Anita": 1,
    "Vulnerables": 1,
    "India": 1,
    "Mype": 1,
    "Pulitzer": 1,
    "Responde": 1,
    "Selección": 1,
    "Kits": 1,
    "Presentó": 1,
    "Iluminación": 1,
    "Estrenan": 1,
    "Podrán": 2,
    "Urbanos": 1,
    "Quechua": 1,
    "Cara": 3,
    "Sabogal": 1,
    "Alertó": 1,
    "Oposición": 1,
    "Santa": 1,
    "Iniciativas": 1,
    "Aquel": 1,
    "Debut": 1,
    "Astronautas": 1,
    "Fujimori": 2,
    "Comiendo": 1,
    "Dormir": 1,
    "Película": 1,
    "Poblaciones": 1,
    "Duelo": 2,
    "Sistema": 3,
    "Quiso": 1,
    "Anillo": 1,
    "Lanza": 1,
    "Viviendo": 1,
    "Bate": 1,
    "Nuevamente": 1,
    "Récord": 2,
    "Consejo": 1,
    "Lima": 5,
    "Junta": 1,
    "Judicial": 1,
    "Entraña": 1,
    "Fracasados": 1,
    "Coca": 1,
    "Franco": 1,
    "Johnson": 1,
    "Llegada": 1,
    "Magisteriales": 1,
    "Busca": 1,
    "Pnp": 1,
    "Posible": 2,
    "Candidatos": 1,
    "Constitucional": 1,
    "Montoya": 2,
    "Partido": 3,
    "Continúa": 1,
    "Gareca": 4,
    "Afina": 1,
    "Impedimento": 1,
    "Carrere": 1,
    "Ramos": 1,
    "Uefa": 1,
    "Versus": 1,
    "Retrasarían": 1,
    "Electrónicos": 1,
    "Siendo": 2,
    "Grandes": 1,
    "Marte": 1,
    "Gobierno": 4,
    "Fiscal": 1,
    "Palmas": 1,
    "Castillo": 3,
    "Yazid": 1,
    "Mejor": 1,
    "Megaoperativo": 1,
    "Digital": 2,
    "Champions": 1,
    "Debate": 1,
    "Serenar": 1,
    "Actas": 4,
    "Red": 1,
    "Pendientes": 1,
    "Prueba": 1,
    "Cura": 1,
    "Médico": 1,
    "Caviar": 1,
    "Pandemia": 1,
    "Centro": 3,
    "Utopía": 1,
    "Danilo": 1,
    "Amenazan": 1,
    "Colorado": 1,
    "Certamen": 1,
    "Centenar": 1,
    "Diferenciar": 1,
    "Descubren": 1,
    "Latinos": 1,
    "Afroamericanos": 1,
    "Homeos": 1,
    "Vandalizar": 1,
    "Portavoces": 1,
    "Copa": 4,
    "Onpe": 3,
    "Prado": 1,
    "Conferencia": 1,
    "Población": 1,
    "Avaló": 1,
    "Cientos": 1,
    "Indisciplina": 1,
    "Tan": 1,
    "Reggaetón": 1,
    "Vilo": 1,
    "Afirma": 1,
    "Presidente": 2,
    "Suben": 1,
    "Putin": 2,
    "Batalla": 1,
    "Imparta": 1,
    "Fin": 1,
    "Evaluación": 1,
    "Fujimorista": 1,
    "Bolsa": 2,
    "Residentes": 1,
    "Central": 1,
    "Explota": 1,
    "Minka": 1,
    "Rusia": 1,
    "Subcontratar": 1,
    "Mil": 2,
    "Sangre": 1,
    "Extrema": 1,
    "Peruana": 2,
    "Primera": 1,
    "Juno": 1,
    "Rumbo": 1,
    "Barcelona": 1,
    "Cerca": 1,
    "Avances": 1,
    "Autoridades": 1,
    "Eva": 1,
    "Thais": 1,
    "Emmanuel": 1,
    "Nipona": 1,
    "Blindaje": 1,
    "Suma": 1,
    "Biden": 2,
    "Gana": 2,
    "Compañeros": 1,
    "Aliaga": 1,
    "Feliz": 1,
    "Ciclo": 1,
    "Administrativos": 1,
    "Lapadula": 1,
    "Congresista": 2,
    "Presidencia": 2,
    "Podemos": 1,
    "Cultura": 2,
    "Personal": 1,
    "Air": 1,
    "Bebé": 1,
    "Hogar": 1,
    "Reglamento": 1,
    "Alemania": 1,
    "Rivera": 1,
    "Junio": 3,
    "Intangible": 1,
    "Características": 1,
    "Sjl": 1,
    "Gardenias": 1,
    "Decides": 1,
    "Regresa": 1,
    "Afirmó": 1,
    "Publica": 1,
    "Acción": 1,
    "Friends": 1,
    "Confianza": 2,
    "Fundador": 1,
    "Astrónomos": 1,
    "Astutos": 1,
    "Buds": 1,
    "Esperar": 1,
    "Alimentos": 1,
    "Inpe": 1,
    "Congresistas": 1,
    "Piedra": 1,
    "Oscura": 1,
    "Trasladado": 1,
    "Clínica": 1,
    "Nacional": 3,
    "Cuestión": 2,
    "Nuevas": 1,
    "Trabaja": 1,
    "Netanyahu": 1,
    "Mundial": 1,
    "Civilización": 1
  },
  "el_comercio": {
    "Partido": 1,
    "Debes": 1,
    "Coronavirus": 3,
    "Brasil": 6,
    "Dávila": 1,
    "Feminicidios": 1,
    "Llamados": 1,
    "Premios": 2,
    "Buscaría": 1,
    "Libre": 2,
    "Telón": 1,
    "Historias": 2,
    "Gonzalo": 2,
    "Varela": 1,
    "Gamarra": 1,
    "Merengue": 1,
    "Ramsey": 1,
    "Mitad": 1,
    "Terminará": 1,
    "Preocupación": 1,
    "Restringido": 1,
    "Reclamo": 1,
    "Guzmán": 1,
    "Varía": 1,
    "Advierten": 1,
    "Resultados": 2,
    "Tipo": 2,
    "Lupin": 1,
    "Sacó": 1,
    "Sorpresa": 1,
    "Preguntado": 1,
    "High": 1,
    "Generación": 1,
    "Delito": 1,
    "Wyndham": 1,
    "Presos": 1,
    "Contabilizadas": 1,
    "Ramos": 2,
    "Proceso": 4,
    "Laura": 1,
    "Acerca": 1,
    "Junio": 3,
    "Callao": 3,
    "Autos": 1,
    "Relación": 1,
    "Falsos": 1,
    "Clubes": 1,
    "Incidentes": 1,
    "Junín": 1,
    "Esfuerzos": 1,
    "Empieza": 1,
    "Entrevista": 2,
    "Registra": 1,
    "Francisco": 2,
    "Atentado": 2,
    "Regulación": 1,
    "Pasan": 1,
    "Colombia": 1,
    "Acta": 1,
    "Crece": 1,
    "Campaña": 1,
    "Juntos": 1,
    "Función": 1,
    "Fujimori": 4,
    "Público": 2,
    "Dominicana": 1,
    "Vez": 2,
    "Domingo": 1,
    "Minutos": 1,
    "Tuesta": 1,
    "Dejó": 1,
    "Guía": 1,
    "Avanza": 1,
    "Iglesias": 3,
    "Kitsch": 1,
    "Trágico": 1,
    "Ormeño": 1,
    "Sigue": 1,
    "Debemos": 1,
    "Imitó": 1,
    "Rada": 2,
    "Julio": 1,
    "Armados": 1,
    "Mujer": 1,
    "Castings": 1,
    "Puerta": 1,
    "Asteroide": 1,
    "Cuestión": 1,
    "Hazañas": 1,
    "Revelation": 1,
    "Ser": 3,
    "Detective": 1,
    "Torneo": 1,
    "Vacunación": 1,
    "Organizar": 1,
    "Desactivan": 1,
    "Ver": 2,
    "Meses": 1,
    "Cuáles": 1,
    "Canta": 1,
    "Quién": 1,
    "Increíble": 1,
    "San": 1,
    "Resolvió": 1,
    "Anotarle": 1,
    "Tonto": 1,
    "Captados": 1,
    "Compañías": 1,
    "Cordialidad": 1,
    "Juega": 2,
    "Covid": 8,
    "Paulo": 1,
    "Mare": 1,
    "Chile": 1,
    "Alto": 3,
    "Voz": 2,
    "Certificado": 1,
    "Desinformación": 1,
    "Diez": 1,
    "Sucesor": 1,
    "Isidro": 1,
    "Cochebomba": 1,
    "Supera": 1,
    "Primera": 5,
    "Segunda": 3,
    "Baja": 1,
    "Imitadora": 1,
    "Nombre": 1,
    "Exactas": 1,
    "Ronaldo": 3,
    "Variantes": 1,
    "Martins": 1,
    "Fraude": 3,
    "Verdadera": 1,
    "Extremo": 1,
    "Avanzan": 1,
    "Insólitas": 1,
    "Recuperación": 1,
    "Pausini": 1,
    "Mamá": 1,
    "Solo": 1,
    "Directiva": 1,
    "Transmisión": 1,
    "Carla": 2,
    "Nominaciones": 1,
    "Reacción": 1,
    "Chumpitaz": 1,
    "Miércoles": 2,
    "James": 1,
    "Ideología": 1,
    "Mesa": 4,
    "Flor": 1,
    "Incluso": 1,
    "Comisión": 1,
    "Ley": 1,
    "Cuántos": 1,
    "Fallecidos": 1,
    "Brillante": 1,
    "Italia": 1,
    "Desnudo": 1,
    "Debe": 1,
    "Gales": 1,
    "Mayo": 1,
    "Allanamiento": 1,
    "Electoral": 3,
    "Pareja": 1,
    "Ganando": 1,
    "Abre": 4,
    "Ilegible": 1,
    "Candidatos": 1,
    "Cambio": 2,
    "Saber": 1,
    "Ahora": 1,
    "Neumonía": 1,
    "Errores": 1,
    "Bcr": 1,
    "Merly": 1,
    "Implicarían": 1,
    "Asistencia": 1,
    "Cuándo": 1,
    "Web": 1,
    "Cumbre": 2,
    "Mbappé": 1,
    "Asaltos": 1,
    "Declarada": 1,
    "Streaming": 1,
    "Gareca": 2,
    "Sars": 1,
    "Ambos": 1,
    "Ola": 1,
    "Olímpico": 1,
    "Principio": 1,
    "Hace": 1,
    "Hospitalización": 1,
    "Alcaldesa": 1,
    "Economía": 1,
    "Conoce": 3,
    "Encuentran": 2,
    "Justifica": 1,
    "Inviable": 1,
    "Nivel": 3,
    "Congreso": 1,
    "Ventas": 1,
    "Película": 1,
    "Familia": 1,
    "Calles": 1,
    "Viceministro": 1,
    "Dólar": 2,
    "Semanas": 1,
    "Breves": 1,
    "Calificó": 1,
    "Delitos": 1,
    "Coca": 2,
    "Aprendido": 1,
    "Hbo": 1,
    "Contagios": 1,
    "Padre": 2,
    "Musical": 1,
    "Proclamará": 1,
    "Nueve": 1,
    "Multidisciplinarios": 1,
    "Casos": 5,
    "Aquí": 2,
    "Recibió": 1,
    "Incidencia": 1,
    "Sergio": 2,
    "Paul": 1,
    "Perder": 2,
    "Cueva": 3,
    "Buscan": 1,
    "Ausentes": 1,
    "Circulación": 1,
    "Burradas": 1,
    "Den": 1,
    "Puertas": 1,
    "Papá": 1,
    "Cov": 1,
    "Uruguay": 1,
    "Ginebra": 1,
    "Decisivo": 1,
    "Cayo": 1,
    "Debido": 1,
    "Díaz": 1,
    "Conmebol": 1,
    "Jueves": 1,
    "Horas": 1,
    "Interviniendo": 1,
    "Muertos": 1,
    "Retos": 1,
    "Karol": 1,
    "Referente": 1,
    "Endurecer": 1,
    "Jne": 4,
    "Corazón": 1,
    "Mejor": 1,
    "Debut": 1,
    "Azares": 1,
    "Vivo": 1,
    "Caso": 2,
    "Edición": 1,
    "Argentina": 1,
    "Arequipa": 1,
    "Loki": 1,
    "Reporta": 1,
    "Vale": 1,
    "Conformación": 1,
    "Fake": 1,
    "Messi": 1,
    "Divorcio": 1,
    "Expertos": 2,
    "Opinan": 1,
    "Quid": 1,
    "Así": 4,
    "Protagonista": 1,
    "Salir": 1,
    "Gol": 2,
    "Día": 2,
    "Menos": 2,
    "Influencia": 1,
    "Ayudará": 1,
    "Soldado": 1,
    "Cerca": 2,
    "Direcciones": 1,
    "Hecho": 1,
    "Quesada": 2,
    "Seguir": 1,
    "Ronald": 1,
    "Millones": 2,
    "Castillo": 1,
    "Reportan": 1,
    "Anular": 2,
    "Despedirá": 1,
    "Dinámicos": 2,
    "Elecciones": 5,
    "Putin": 3,
    "Niños": 1,
    "Dos": 1,
    "Dominan": 1,
    "Mourinho": 1,
    "Pogba": 1,
    "Apps": 1,
    "Sitios": 1,
    "Tema": 1,
    "Comercio": 1,
    "Guillermo": 1,
    "Rebelan": 1,
    "Awapara": 1,
    "Uso": 1,
    "Basombrío": 2,
    "País": 2,
    "Preguntas": 1,
    "Oposición": 1,
    "Grupos": 1,
    "Gestionar": 1,
    "Dolartoday": 1,
    "Pueblo": 1,
    "Romeo": 1,
    "Análisis": 1,
    "Kate": 1,
    "Consagra": 1,
    "Culpan": 1,
    "Disciplinario": 1,
    "Gobierno": 2,
    "Madre": 1,
    "Expectativas": 1,
    "Soles": 1,
    "Predicciones": 1,
    "Malas": 1,
    "Precios": 1,
    "Judicial": 1,
    "Basile": 1,
    "Biden": 2,
    "Pantalla": 1,
    "Casi": 2,
    "Descartó": 2,
    "Disney": 2,
    "Banda": 2,
    "Cristiano": 3,
    "Plena": 1,
    "Privado": 1,
    "Deja": 2,
    "Madrid": 1,
    "Inmunización": 1,
    "París": 1,
    "Expresiones": 1,
    "Selección": 2,
    "Luz": 1,
    "Asprilla": 1,
    "Carlos": 2,
    "Recibir": 1,
    "Analizan": 1,
    "Francia": 1,
    "Niñas": 1,
    "Articular": 1,
    "Médicos": 1,
    "Coco": 1,
    "Salieron": 1,
    "Municipal": 1,
    "Cine": 1,
    "Suiza": 1,
    "Superación": 1,
    "Quejas": 1,
    "Lima": 4,
    "Centro": 2,
    "School": 1,
    "Histórica": 1,
    "Sao": 1,
    "Universe": 1,
    "Llegó": 2,
    "América": 6,
    "Real": 1,
    "Blanca": 1,
    "Mal": 1,
    "Estudia": 1,
    "Tan": 1,
    "Separación": 1,
    "Torno": 1,
    "Activos": 1,
    "Volver": 1,
    "Málaga": 1,
    "Inicia": 1,
    "Respuestas": 1,
    "Luca": 1,
    "Aplican": 1,
    "Stephanie": 1,
    "Agotar": 1,
    "Israel": 1,
    "Excluye": 1,
    "Capitán": 1,
    "Parejas": 1,
    "Omar": 2,
    "Millón": 2,
    "Dosis": 3,
    "Fallecimientos": 2,
    "Sorprender": 1,
    "Concursante": 1,
    "Juventud": 1,
    "Intercambio": 1,
    "Seguirá": 1,
    "Revise": 1,
    "Vulnerables": 1,
    "Salud": 1,
    "Sedición": 1,
    "Club": 1,
    "Mayores": 2,
    "Apelaciones": 2,
    "Futuro": 1,
    "Laboral": 1,
    "Winslet": 1,
    "Casas": 1,
    "Lionel": 1,
    "Keiko": 1,
    "Adultos": 1,
    "Historia": 1,
    "Delivery": 2,
    "Nueva": 2,
    "Pandemia": 2,
    "Medio": 2,
    "Vivas": 2,
    "Triunfar": 1,
    "Actores": 1,
    "Miró": 2,
    "Temporada": 1,
    "Hoteles": 1,
    "Bien": 1,
    "Precio": 2,
    "Posible": 1,
    "Exclusiva": 1,
    "Turquía": 1,
    "Hoy": 3,
    "Podcast": 1,
    "Digital": 1,
    "Neymar": 1,
    "Inmovilización": 1,
    "Easttown": 1,
    "Venta": 1,
    "Man": 1,
    "Incertidumbre": 1,
    "Poder": 1,
    "Amoroso": 1,
    "Interior": 1,
    "Martín": 2,
    "Unidad": 1,
    "Roma": 1,
    "Domingos": 1,
    "Copa": 6,
    "Odebrecht": 1,
    "Límite": 1,
    "Cúcuta": 2,
    "Aforos": 1,
    "Offside": 1,
    "Soberano": 1,
    "Bale": 1,
    "Felicitó": 1,
    "Volante": 1,
    "Interpretación": 1,
    "Venezuela": 1,
    "Suma": 1,
    "Votos": 1,
    "Crítica": 1,
    "Casa": 1,
    "Casarse": 1,
    "Enturbia": 1,
    "Mercado": 1,
    "Enseñando": 1,
    "República": 1,
    "Peruana": 2,
    "Propuesto": 1,
    "Cuán": 1,
    "Ausencia": 1,
    "Coya": 2,
    "Repetir": 1,
    "Hablan": 1,
    "Héctor": 1,
    "News": 1,
    "Consejos": 1,
    "Luego": 1,
    "Botella": 1,
    "Firmeza": 1,
    "Observadas": 1,
    "Irregularidades": 1,
    "Netflix": 1,
    "Medidas": 2,
    "Anne": 1,
    "Tercera": 1,
    "Detrás": 1,
    "Encender": 1,
    "Susy": 1,
    "Coche": 1,
    "Funciona": 1,
    "Santos": 1,
    "Crecer": 1,
    "Elige": 1,
    "Masters": 1,
    "Cuesta": 1,
    "Enteraron": 1,
    "Serie": 3,
    "Personas": 1,
    "Opciones": 1,
    "Garantiza": 1,
    "Democracia": 3,
    "José": 1,
    "Ops": 1,
    "Vladimir": 2,
    "Jurisdiccional": 1,
    "Respuesta": 1,
    "Centros": 1,
    "Ricardo": 1,
    "Editorial": 2,
    "Ahí": 1,
    "Forzando": 1,
    "Espacio": 1,
    "Incautan": 1,
    "Cerrón": 2,
    "Hidalgo": 1,
    "Heridos": 1,
    "Tanaka": 2,
    "Camilo": 1,
    "Hugo": 2,
    "Teatro": 1,
    "Fondo": 1,
    "Analizó": 1,
    "Repartidores": 1,
    "Embajador": 1,
    "Perú": 6,
    "Vamos": 1,
    "Castiglioni": 1,
    "Concurso": 1,
    "Puede": 1,
    "Christian": 2,
    "Cbf": 1,
    "Figura": 1,
    "Vuelta": 2,
    "Razón": 1,
    "Onpe": 1,
    "Gamberini": 2,
    "Cambiario": 1,
    "Sabía": 1,
    "Capítulo": 1,
    "Netanyahu": 1,
    "Construcción": 1,
    "Cerveza": 1,
    "Robos": 1,
    "Pide": 1,
    "Convocar": 1,
    "Salas": 1,
    "Maxi": 1,
    "Abril": 1,
    "Bomba": 1,
    "Fernando": 3,
    "Efectos": 1,
    "Negociaciones": 1,
    "Signo": 1,
    "Zodiacal": 1,
    "Resolver": 1,
    "Pixar": 1,
    "Soldevilla": 1,
    "Viajeros": 1,
    "Segundo": 1,
    "Ocurre": 1,
    "Joe": 1,
    "Intervención": 1,
    "Provincias": 1,
    "Trajo": 1,
    "Actas": 2,
    "Cola": 2,
    "Nuevos": 4,
    "Prometen": 1,
    "Identifica": 1,
    "Cantada": 1,
    "Retama": 1,
    "Nuevas": 1,
    "Instancia": 1,
    "Brasileños": 1,
    "Alquiler": 1,
    "Unidos": 1,
    "Nadia": 1,
    "Horóscopo": 1,
    "Riesgo": 3,
    "Murciélago": 1,
    "España": 2,
    "Acciones": 1,
    "Probable": 1,
    "Gay": 1,
    "Restrictivas": 1,
    "Países": 1,
    "Camino": 1,
    "Presidenta": 1,
    "Habló": 1,
    "Coz": 1,
    "Alta": 1
  }
}